{"tgs":1,"v":"5.5.2","fr":60,"ip":60,"op":240,"w":512,"h":512,"nm":"_118_SRCH_AI","ddd":0,"assets":[],"layers":[{"ddd":0,"ind":1,"ty":4,"nm":"Shape Layer 1","sr":1,"ks":{"o":{"a":0,"k":20},"p":{"a":1,"k":[{"i":{"x":0.667,"y":1},"o":{"x":0.333,"y":0},"t":15,"s":[186,492.016,0],"to":[0,0,0],"ti":[0,0,0]},{"i":{"x":0.667,"y":1},"o":{"x":0.333,"y":0},"t":75,"s":[266,492.016,0],"to":[0,0,0],"ti":[0,0,0]},{"i":{"x":0.667,"y":1},"o":{"x":0.333,"y":0},"t":140,"s":[286,492.016,0],"to":[0,0,0],"ti":[0,0,0]},{"i":{"x":0.667,"y":1},"o":{"x":0.333,"y":0},"t":195,"s":[186,492.016,0],"to":[0,0,0],"ti":[0,0,0]},{"t":255,"s":[266,492.016,0]}]},"a":{"a":0,"k":[113.492,192.016,0]},"s":{"a":1,"k":[{"i":{"x":[0.667,0.667,0.667],"y":[1,1,1]},"o":{"x":[0.333,0.333,0.333],"y":[0,0,0]},"t":60,"s":[76.517,37.044,100]},{"i":{"x":[0.667,0.667,0.667],"y":[1,1,1]},"o":{"x":[0.333,0.333,0.333],"y":[0,0,0]},"t":75,"s":[86.517,41.885,100]},{"i":{"x":[0.667,0.667,0.667],"y":[1,1,1]},"o":{"x":[0.333,0.333,0.333],"y":[0,0,0]},"t":90,"s":[76.517,37.044,100]},{"i":{"x":[0.667,0.667,0.667],"y":[1,1,1]},"o":{"x":[0.333,0.333,0.333],"y":[0,0,0]},"t":105,"s":[86.517,41.885,100]},{"i":{"x":[0.667,0.667,0.667],"y":[1,1,1]},"o":{"x":[0.333,0.333,0.333],"y":[0,0,0]},"t":120,"s":[76.517,37.044,100]},{"i":{"x":[0.667,0.667,0.667],"y":[1,1,1]},"o":{"x":[0.333,0.333,0.333],"y":[0,0,0]},"t":135,"s":[86.517,41.885,100]},{"i":{"x":[0.667,0.667,0.667],"y":[1,1,1]},"o":{"x":[0.333,0.333,0.333],"y":[0,0,0]},"t":150,"s":[76.517,37.044,100]},{"i":{"x":[0.667,0.667,0.667],"y":[1,1,1]},"o":{"x":[0.333,0.333,0.333],"y":[0,0,0]},"t":165,"s":[86.517,41.885,100]},{"i":{"x":[0.667,0.667,0.667],"y":[1,1,1]},"o":{"x":[0.333,0.333,0.333],"y":[0,0,0]},"t":180,"s":[76.517,37.044,100]},{"i":{"x":[0.667,0.667,0.667],"y":[1,1,1]},"o":{"x":[0.333,0.333,0.333],"y":[0,0,0]},"t":195,"s":[86.517,41.885,100]},{"i":{"x":[0.667,0.667,0.667],"y":[1,1,1]},"o":{"x":[0.333,0.333,0.333],"y":[0,0,0]},"t":210,"s":[76.517,37.044,100]},{"i":{"x":[0.667,0.667,0.667],"y":[1,1,1]},"o":{"x":[0.333,0.333,0.333],"y":[0,0,0]},"t":225,"s":[86.517,41.885,100]},{"t":240,"s":[76.517,37.044,100]}]}},"ao":0,"shapes":[{"ty":"gr","it":[{"d":1,"ty":"el","s":{"a":0,"k":[246.984,62.031]},"p":{"a":0,"k":[0,0]},"nm":"Ellipse Path 1","hd":false},{"ty":"fl","c":{"a":0,"k":[0,0.432892952713,0.549034926471,1]},"o":{"a":0,"k":100},"r":1,"bm":0,"nm":"Fill 1","hd":false},{"ty":"tr","p":{"a":0,"k":[113.492,192.016]},"a":{"a":0,"k":[0,0]},"s":{"a":0,"k":[100,100]},"r":{"a":0,"k":0},"o":{"a":0,"k":100},"sk":{"a":0,"k":0},"sa":{"a":0,"k":0},"nm":"Transform"}],"nm":"Ellipse 1","bm":0,"hd":false}],"ip":0,"op":300,"st":0,"bm":0},{"ddd":0,"ind":2,"ty":3,"nm":"Null 1268","sr":1,"ks":{"o":{"a":0,"k":0},"p":{"a":0,"k":[256,256,0]}},"ao":0,"ip":0,"op":300,"st":0,"bm":0},{"ddd":0,"ind":3,"ty":4,"nm":"wing","parent":22,"sr":1,"ks":{"r":{"a":0,"k":-30.389},"p":{"a":1,"k":[{"i":{"x":0.667,"y":1},"o":{"x":0.333,"y":0},"t":68,"s":[-115.135,72.197,0],"to":[0,0,0],"ti":[0,0,0]},{"i":{"x":0.667,"y":1},"o":{"x":0.333,"y":0},"t":85,"s":[-124.402,67.332,0],"to":[0,0,0],"ti":[0,0,0]},{"i":{"x":0.667,"y":1},"o":{"x":0.333,"y":0},"t":100,"s":[-134.85,61.848,0],"to":[0,0,0],"ti":[0,0,0]},{"i":{"x":0.667,"y":0.667},"o":{"x":0.333,"y":0.333},"t":127,"s":[-134.85,82.319,0],"to":[0,0,0],"ti":[0,0,0]},{"i":{"x":0.667,"y":1},"o":{"x":0.333,"y":0},"t":140,"s":[-134.85,82.319,0],"to":[0,0,0],"ti":[0,0,0]},{"i":{"x":0.667,"y":0.667},"o":{"x":0.333,"y":0.333},"t":158,"s":[-154.815,62.235,0],"to":[0,0,0],"ti":[0,0,0]},{"i":{"x":0.667,"y":0.667},"o":{"x":0.333,"y":0.333},"t":171,"s":[-154.815,62.235,0],"to":[0,0,0],"ti":[0,0,0]},{"i":{"x":0.667,"y":1},"o":{"x":0.333,"y":0},"t":184,"s":[-154.815,62.235,0],"to":[0,0,0],"ti":[0,0,0]},{"t":213,"s":[-115.135,72.197,0]}]},"a":{"a":0,"k":[-39.135,100.197,0]}},"ao":0,"shapes":[{"ty":"gr","it":[{"ind":0,"ty":"sh","ks":{"a":1,"k":[{"i":{"x":0.667,"y":1},"o":{"x":0.333,"y":0},"t":68,"s":[{"i":[[0,0],[-8.196,8.866]],"o":[[6.749,-9.899],[0,0]],"v":[[-104.937,144.96],[-83.443,117.587]],"c":false}]},{"i":{"x":0.667,"y":1},"o":{"x":0.333,"y":0},"t":85,"s":[{"i":[[0,0],[-9.372,7.328]],"o":[[8.129,-8.561],[0,0]],"v":[[-107.073,143.448],[-81.842,120.22]],"c":false}]},{"i":{"x":0.667,"y":1},"o":{"x":0.333,"y":0},"t":100,"s":[{"i":[[0,0],[-9.162,7.863]],"o":[[7.845,-9.056],[0,0]],"v":[[-107.855,151.524],[-79.143,127.537]],"c":false}]},{"i":{"x":0.667,"y":1},"o":{"x":0.333,"y":0},"t":127,"s":[{"i":[[0,0],[-6.376,10.253]],"o":[[4.761,-10.994],[0,0]],"v":[[-71.063,153.368],[-55.119,122.431]],"c":false}]},{"i":{"x":0.667,"y":1},"o":{"x":0.333,"y":0},"t":140,"s":[{"i":[[0,0],[-6.376,10.253]],"o":[[4.761,-10.994],[0,0]],"v":[[-71.063,153.368],[-55.119,122.431]],"c":false}]},{"i":{"x":0.667,"y":1},"o":{"x":0.333,"y":0},"t":158,"s":[{"i":[[0,0],[-8.282,7.661]],"o":[[13.577,-9.857],[0,0]],"v":[[-76.072,146.11],[-49.366,122.403]],"c":false}]},{"i":{"x":0.667,"y":1},"o":{"x":0.333,"y":0},"t":171,"s":[{"i":[[0,0],[-8.282,7.661]],"o":[[10.156,-10.754],[0,0]],"v":[[-79.188,144.528],[-55.825,119.688]],"c":false}]},{"i":{"x":0.667,"y":1},"o":{"x":0.333,"y":0},"t":184,"s":[{"i":[[0,0],[-8.282,7.661]],"o":[[10.156,-10.754],[0,0]],"v":[[-74.537,147.465],[-51.175,122.625]],"c":false}]},{"t":213,"s":[{"i":[[0,0],[-8.196,8.866]],"o":[[6.749,-9.899],[0,0]],"v":[[-104.937,144.96],[-83.443,117.587]],"c":false}]}]},"nm":"Path 1","hd":false},{"ty":"st","c":{"a":0,"k":[1,1,1,1]},"o":{"a":0,"k":100},"w":{"a":0,"k":8},"lc":2,"lj":2,"bm":0,"nm":"Stroke 1","hd":false},{"ty":"tr","p":{"a":0,"k":[0,0]},"a":{"a":0,"k":[0,0]},"s":{"a":0,"k":[100,100]},"r":{"a":0,"k":0},"o":{"a":0,"k":100},"sk":{"a":0,"k":0},"sa":{"a":0,"k":0},"nm":"Transform"}],"nm":"Group 1","bm":0,"hd":false},{"ty":"gr","it":[{"ind":0,"ty":"sh","ks":{"a":1,"k":[{"i":{"x":0.667,"y":1},"o":{"x":0.333,"y":0},"t":68,"s":[{"i":[[0,0],[9.641,5.214],[-36.397,28.234]],"o":[[-31.092,25.684],[-7.563,-4.09],[0,0]],"v":[[-44.34,131.993],[-122.884,167.728],[-71.864,94.247]],"c":false}]},{"i":{"x":0.667,"y":1},"o":{"x":0.333,"y":0},"t":85,"s":[{"i":[[0,0],[8.553,6.596],[-39.863,21.709]],"o":[[-34.3,20.067],[-6.71,-5.174],[0,0]],"v":[[-46.086,140.413],[-128.127,162.756],[-66.891,99.349]],"c":false}]},{"i":{"x":0.667,"y":1},"o":{"x":0.333,"y":0},"t":100,"s":[{"i":[[0,0],[8.977,6.29],[-39.407,23.854]],"o":[[-33.843,21.932],[-7.042,-4.934],[0,0]],"v":[[-45.886,148.106],[-128.305,172.073],[-64.953,105.686]],"c":false}]},{"i":{"x":0.667,"y":1},"o":{"x":0.333,"y":0},"t":127,"s":[{"i":[[0,0],[10.452,3.302],[-30.417,34.594]],"o":[[-25.688,31.088],[-8.199,-2.59],[0,0]],"v":[[-11.761,126.362],[-84.392,179.112],[-51.685,102.373]],"c":false}]},{"i":{"x":0.667,"y":1},"o":{"x":0.333,"y":0},"t":140,"s":[{"i":[[0,0],[10.452,3.302],[-30.417,34.594]],"o":[[-25.688,31.088],[-8.199,-2.59],[0,0]],"v":[[-11.761,126.362],[-84.392,179.112],[-51.685,102.373]],"c":false}]},{"i":{"x":0.667,"y":1},"o":{"x":0.333,"y":0},"t":158,"s":[{"i":[[0,0],[10.452,3.302],[-39.197,33.14]],"o":[[-23.653,20.142],[-8.199,-2.59],[0,0]],"v":[[-43.836,136.655],[-100.521,166.161],[-47.355,107.91]],"c":false}]},{"i":{"x":0.667,"y":1},"o":{"x":0.333,"y":0},"t":171,"s":[{"i":[[0,0],[10.452,3.302],[-39.197,33.14]],"o":[[-23.653,20.142],[-8.199,-2.59],[0,0]],"v":[[-43.836,136.655],[-100.521,166.161],[-53.132,103.853]],"c":false}]},{"i":{"x":0.667,"y":1},"o":{"x":0.333,"y":0},"t":184,"s":[{"i":[[0,0],[10.452,3.302],[-39.197,33.14]],"o":[[-23.653,20.142],[-8.199,-2.59],[0,0]],"v":[[-39.186,139.592],[-95.871,169.097],[-48.481,106.789]],"c":false}]},{"t":213,"s":[{"i":[[0,0],[9.641,5.214],[-36.397,28.234]],"o":[[-31.092,25.684],[-7.563,-4.09],[0,0]],"v":[[-44.34,131.993],[-122.884,167.728],[-71.864,94.247]],"c":false}]}]},"nm":"Path 1","hd":false},{"ty":"st","c":{"a":0,"k":[0.533333333333,0.737254901961,0.870588235294,1]},"o":{"a":0,"k":100},"w":{"a":0,"k":10},"lc":2,"lj":2,"bm":0,"nm":"Stroke 1","hd":false},{"ty":"fl","c":{"a":0,"k":[1,1,1,1]},"o":{"a":0,"k":100},"r":1,"bm":0,"nm":"Fill 1","hd":false},{"ty":"tr","p":{"a":0,"k":[0,0]},"a":{"a":0,"k":[0,0]},"s":{"a":0,"k":[100,100]},"r":{"a":0,"k":0},"o":{"a":0,"k":100},"sk":{"a":0,"k":0},"sa":{"a":0,"k":0},"nm":"Transform"}],"nm":"Group 2","bm":0,"hd":false}],"ip":0,"op":300,"st":0,"bm":0},{"ddd":0,"ind":4,"ty":4,"nm":"lupa11","parent":5,"sr":1,"ks":{"o":{"a":0,"k":50},"r":{"a":0,"k":180},"s":{"a":0,"k":[100,102.141,100]}},"ao":0,"shapes":[{"ty":"gr","it":[{"ind":0,"ty":"sh","ks":{"a":1,"k":[{"i":{"x":0.667,"y":1},"o":{"x":0.333,"y":0},"t":68,"s":[{"i":[[-2.139,0.427],[-4.327,-4.127]],"o":[[3.056,-0.611],[0.583,0.556]],"v":[[-0.847,-27.713],[15.929,-21.894]],"c":false}]},{"i":{"x":0.667,"y":1},"o":{"x":0.333,"y":0},"t":86,"s":[{"i":[[-1.66,1.415],[-5.79,-1.497]],"o":[[2.372,-2.022],[0.78,0.202]],"v":[[-12.923,-22.552],[4.563,-25.64]],"c":false}]},{"i":{"x":0.667,"y":1},"o":{"x":0.333,"y":0},"t":100,"s":[{"i":[[-1.66,1.415],[-5.79,-1.497]],"o":[[2.372,-2.022],[0.78,0.202]],"v":[[-12.923,-22.552],[4.563,-25.64]],"c":false}]},{"i":{"x":0.667,"y":1},"o":{"x":0.333,"y":0},"t":114,"s":[{"i":[[-2.139,0.427],[-4.327,-4.127]],"o":[[3.056,-0.611],[0.583,0.556]],"v":[[-0.847,-27.713],[15.929,-21.894]],"c":false}]},{"i":{"x":0.667,"y":1},"o":{"x":0.333,"y":0},"t":140,"s":[{"i":[[-2.139,0.427],[-4.327,-4.127]],"o":[[3.056,-0.611],[0.583,0.556]],"v":[[-0.847,-27.713],[15.929,-21.894]],"c":false}]},{"i":{"x":0.667,"y":1},"o":{"x":0.333,"y":0},"t":158,"s":[{"i":[[-2.084,0.643],[-4.726,-3.664]],"o":[[2.978,-0.919],[0.637,0.494]],"v":[[-8.57,-28.991],[8.712,-24.913]],"c":false}]},{"i":{"x":0.667,"y":1},"o":{"x":0.333,"y":0},"t":184,"s":[{"i":[[-2.084,0.643],[-4.726,-3.664]],"o":[[2.978,-0.919],[0.637,0.494]],"v":[[-8.57,-28.991],[8.712,-24.913]],"c":false}]},{"t":199,"s":[{"i":[[-2.139,0.427],[-4.327,-4.127]],"o":[[3.056,-0.611],[0.583,0.556]],"v":[[-0.847,-27.713],[15.929,-21.894]],"c":false}]}]},"nm":"Path 1","hd":false},{"ty":"st","c":{"a":0,"k":[1,1,1,1]},"o":{"a":0,"k":100},"w":{"a":0,"k":6},"lc":2,"lj":2,"bm":0,"nm":"Stroke 1","hd":false},{"ty":"tr","p":{"a":0,"k":[0,0]},"a":{"a":0,"k":[0,0]},"s":{"a":0,"k":[100,100]},"r":{"a":0,"k":0},"o":{"a":0,"k":100},"sk":{"a":0,"k":0},"sa":{"a":0,"k":0},"nm":"Transform"}],"nm":"Group 1","bm":0,"hd":false},{"ty":"tm","s":{"a":1,"k":[{"i":{"x":[0.667],"y":[1]},"o":{"x":[0.333],"y":[0]},"t":60,"s":[5]},{"i":{"x":[0.667],"y":[1]},"o":{"x":[0.333],"y":[0]},"t":72,"s":[0]},{"i":{"x":[0.667],"y":[1]},"o":{"x":[0.333],"y":[0]},"t":84,"s":[5]},{"i":{"x":[0.667],"y":[1]},"o":{"x":[0.333],"y":[0]},"t":96,"s":[0]},{"i":{"x":[0.667],"y":[1]},"o":{"x":[0.333],"y":[0]},"t":108,"s":[5]},{"i":{"x":[0.667],"y":[1]},"o":{"x":[0.333],"y":[0]},"t":120,"s":[0]},{"i":{"x":[0.667],"y":[1]},"o":{"x":[0.333],"y":[0]},"t":132,"s":[5]},{"i":{"x":[0.667],"y":[1]},"o":{"x":[0.333],"y":[0]},"t":144,"s":[0]},{"i":{"x":[0.667],"y":[1]},"o":{"x":[0.333],"y":[0]},"t":156,"s":[5]},{"i":{"x":[0.667],"y":[1]},"o":{"x":[0.333],"y":[0]},"t":168,"s":[5]},{"i":{"x":[0.667],"y":[1]},"o":{"x":[0.333],"y":[0]},"t":180,"s":[0]},{"i":{"x":[0.667],"y":[1]},"o":{"x":[0.333],"y":[0]},"t":192,"s":[5]},{"i":{"x":[0.667],"y":[1]},"o":{"x":[0.333],"y":[0]},"t":204,"s":[0]},{"i":{"x":[0.667],"y":[1]},"o":{"x":[0.333],"y":[0]},"t":216,"s":[5]},{"i":{"x":[0.667],"y":[1]},"o":{"x":[0.167],"y":[0]},"t":228,"s":[0]},{"t":240,"s":[5]}]},"e":{"a":1,"k":[{"i":{"x":[0.667],"y":[1]},"o":{"x":[0.333],"y":[0]},"t":60,"s":[100]},{"i":{"x":[0.667],"y":[1]},"o":{"x":[0.333],"y":[0]},"t":72,"s":[95]},{"i":{"x":[0.667],"y":[1]},"o":{"x":[0.333],"y":[0]},"t":84,"s":[100]},{"i":{"x":[0.667],"y":[1]},"o":{"x":[0.333],"y":[0]},"t":96,"s":[95]},{"i":{"x":[0.667],"y":[1]},"o":{"x":[0.333],"y":[0]},"t":108,"s":[100]},{"i":{"x":[0.667],"y":[1]},"o":{"x":[0.333],"y":[0]},"t":120,"s":[95]},{"i":{"x":[0.667],"y":[1]},"o":{"x":[0.333],"y":[0]},"t":132,"s":[100]},{"i":{"x":[0.667],"y":[1]},"o":{"x":[0.333],"y":[0]},"t":144,"s":[95]},{"i":{"x":[0.667],"y":[1]},"o":{"x":[0.333],"y":[0]},"t":156,"s":[100]},{"i":{"x":[0.667],"y":[1]},"o":{"x":[0.333],"y":[0]},"t":168,"s":[100]},{"i":{"x":[0.667],"y":[1]},"o":{"x":[0.333],"y":[0]},"t":180,"s":[95]},{"i":{"x":[0.667],"y":[1]},"o":{"x":[0.333],"y":[0]},"t":192,"s":[100]},{"i":{"x":[0.667],"y":[1]},"o":{"x":[0.333],"y":[0]},"t":204,"s":[95]},{"i":{"x":[0.667],"y":[1]},"o":{"x":[0.333],"y":[0]},"t":216,"s":[100]},{"i":{"x":[0.667],"y":[1]},"o":{"x":[0.167],"y":[0]},"t":228,"s":[95]},{"t":240,"s":[100]}]},"o":{"a":0,"k":0},"m":1,"nm":"Trim Paths 1","hd":false}],"ip":60,"op":240,"st":60,"bm":0},{"ddd":0,"ind":5,"ty":4,"nm":"lupa10","parent":7,"sr":1,"ks":{},"ao":0,"shapes":[{"ty":"gr","it":[{"ind":0,"ty":"sh","ks":{"a":1,"k":[{"i":{"x":0.667,"y":1},"o":{"x":0.333,"y":0},"t":68,"s":[{"i":[[-1.622,-0.061],[-2.349,-2.735]],"o":[[6.306,0.238],[0.768,0.894]],"v":[[-0.876,-10.128],[12.98,-5.34]],"c":false}]},{"i":{"x":0.667,"y":1},"o":{"x":0.333,"y":0},"t":86,"s":[{"i":[[-1.355,0.894],[-3.502,-0.859]],"o":[[5.268,-3.474],[1.145,0.281]],"v":[[-13.739,-21.435],[0.317,-25.599]],"c":false}]},{"i":{"x":0.667,"y":1},"o":{"x":0.333,"y":0},"t":100,"s":[{"i":[[-1.355,0.894],[-3.502,-0.859]],"o":[[5.268,-3.474],[1.145,0.281]],"v":[[-13.739,-21.435],[0.317,-25.599]],"c":false}]},{"i":{"x":0.667,"y":1},"o":{"x":0.333,"y":0},"t":114,"s":[{"i":[[-1.622,-0.061],[-2.349,-2.735]],"o":[[6.306,0.238],[0.768,0.894]],"v":[[-0.876,-10.128],[12.98,-5.34]],"c":false}]},{"i":{"x":0.667,"y":1},"o":{"x":0.333,"y":0},"t":140,"s":[{"i":[[-1.622,-0.061],[-2.349,-2.735]],"o":[[6.306,0.238],[0.768,0.894]],"v":[[-0.876,-10.128],[12.98,-5.34]],"c":false}]},{"i":{"x":0.667,"y":1},"o":{"x":0.333,"y":0},"t":158,"s":[{"i":[[-1.611,0.197],[-2.754,-2.328]],"o":[[6.264,-0.767],[0.9,0.761]],"v":[[-6.857,-8.696],[7.584,-6.17]],"c":false}]},{"i":{"x":0.667,"y":1},"o":{"x":0.333,"y":0},"t":184,"s":[{"i":[[-1.611,0.197],[-2.754,-2.328]],"o":[[6.264,-0.767],[0.9,0.761]],"v":[[-6.857,-8.696],[7.584,-6.17]],"c":false}]},{"t":199,"s":[{"i":[[-1.622,-0.061],[-2.349,-2.735]],"o":[[6.306,0.238],[0.768,0.894]],"v":[[-0.876,-10.128],[12.98,-5.34]],"c":false}]}]},"nm":"Path 1","hd":false},{"ty":"st","c":{"a":0,"k":[1,1,1,1]},"o":{"a":0,"k":100},"w":{"a":0,"k":8},"lc":2,"lj":2,"bm":0,"nm":"Stroke 1","hd":false},{"ty":"tr","p":{"a":0,"k":[0,0]},"a":{"a":0,"k":[0,0]},"s":{"a":0,"k":[100,100]},"r":{"a":0,"k":0},"o":{"a":0,"k":100},"sk":{"a":0,"k":0},"sa":{"a":0,"k":0},"nm":"Transform"}],"nm":"Group 1","bm":0,"hd":false},{"ty":"tm","s":{"a":1,"k":[{"i":{"x":[0.667],"y":[1]},"o":{"x":[0.333],"y":[0]},"t":60,"s":[20]},{"i":{"x":[0.667],"y":[1]},"o":{"x":[0.333],"y":[0]},"t":72,"s":[10]},{"i":{"x":[0.667],"y":[1]},"o":{"x":[0.333],"y":[0]},"t":84,"s":[10]},{"i":{"x":[0.667],"y":[1]},"o":{"x":[0.333],"y":[0]},"t":96,"s":[5]},{"i":{"x":[0.667],"y":[1]},"o":{"x":[0.333],"y":[0]},"t":108,"s":[20]},{"i":{"x":[0.667],"y":[1]},"o":{"x":[0.333],"y":[0]},"t":120,"s":[10]},{"i":{"x":[0.667],"y":[1]},"o":{"x":[0.333],"y":[0]},"t":132,"s":[10]},{"i":{"x":[0.667],"y":[1]},"o":{"x":[0.333],"y":[0]},"t":144,"s":[5]},{"i":{"x":[0.667],"y":[1]},"o":{"x":[0.333],"y":[0]},"t":156,"s":[20]},{"i":{"x":[0.667],"y":[1]},"o":{"x":[0.333],"y":[0]},"t":168,"s":[10]},{"i":{"x":[0.667],"y":[1]},"o":{"x":[0.333],"y":[0]},"t":180,"s":[10]},{"i":{"x":[0.667],"y":[1]},"o":{"x":[0.333],"y":[0]},"t":192,"s":[10]},{"i":{"x":[0.667],"y":[1]},"o":{"x":[0.333],"y":[0]},"t":204,"s":[5]},{"i":{"x":[0.667],"y":[1]},"o":{"x":[0.333],"y":[0]},"t":216,"s":[20]},{"i":{"x":[0.667],"y":[1]},"o":{"x":[0.333],"y":[0]},"t":228,"s":[10]},{"t":240,"s":[20]}]},"e":{"a":1,"k":[{"i":{"x":[0.667],"y":[1]},"o":{"x":[0.333],"y":[0]},"t":60,"s":[100]},{"i":{"x":[0.667],"y":[1]},"o":{"x":[0.333],"y":[0]},"t":72,"s":[80]},{"i":{"x":[0.667],"y":[1]},"o":{"x":[0.333],"y":[0]},"t":84,"s":[90]},{"i":{"x":[0.667],"y":[1]},"o":{"x":[0.333],"y":[0]},"t":96,"s":[70]},{"i":{"x":[0.667],"y":[1]},"o":{"x":[0.333],"y":[0]},"t":108,"s":[100]},{"i":{"x":[0.667],"y":[1]},"o":{"x":[0.333],"y":[0]},"t":120,"s":[80]},{"i":{"x":[0.667],"y":[1]},"o":{"x":[0.333],"y":[0]},"t":132,"s":[90]},{"i":{"x":[0.667],"y":[1]},"o":{"x":[0.333],"y":[0]},"t":144,"s":[70]},{"i":{"x":[0.667],"y":[1]},"o":{"x":[0.333],"y":[0]},"t":156,"s":[100]},{"i":{"x":[0.667],"y":[1]},"o":{"x":[0.333],"y":[0]},"t":168,"s":[80]},{"i":{"x":[0.667],"y":[1]},"o":{"x":[0.333],"y":[0]},"t":180,"s":[80]},{"i":{"x":[0.667],"y":[1]},"o":{"x":[0.333],"y":[0]},"t":192,"s":[90]},{"i":{"x":[0.667],"y":[1]},"o":{"x":[0.333],"y":[0]},"t":204,"s":[70]},{"i":{"x":[0.667],"y":[1]},"o":{"x":[0.333],"y":[0]},"t":216,"s":[100]},{"i":{"x":[0.667],"y":[1]},"o":{"x":[0.333],"y":[0]},"t":228,"s":[80]},{"t":240,"s":[100]}]},"o":{"a":0,"k":0},"m":1,"nm":"Trim Paths 1","hd":false}],"ip":60,"op":240,"st":60,"bm":0},{"ddd":0,"ind":6,"ty":4,"nm":"lupa12","parent":7,"sr":1,"ks":{},"ao":0,"shapes":[{"ty":"gr","it":[{"ind":0,"ty":"sh","ks":{"a":1,"k":[{"i":{"x":0.667,"y":1},"o":{"x":0.333,"y":0},"t":68,"s":[{"i":[[13.07,5.995],[5.81,0.629],[5.365,-12.351]],"o":[[-4.782,-2.194],[-18.677,-2.022],[-0.321,0.74]],"v":[[18.741,-17.799],[2.734,-22.142],[-37.973,-3.967]],"c":false}]},{"i":{"x":0.667,"y":1},"o":{"x":0.333,"y":0},"t":86,"s":[{"i":[[13.639,6.224],[5.844,0],[4.004,-17.574]],"o":[[-4.99,-2.277],[-18.786,0],[-0.24,1.053]],"v":[[16.381,-35.954],[0,-39.5],[-38.514,-8.811]],"c":false}]},{"i":{"x":0.667,"y":1},"o":{"x":0.333,"y":0},"t":100,"s":[{"i":[[13.639,6.224],[5.844,0],[4.004,-17.574]],"o":[[-4.99,-2.277],[-18.786,0],[-0.24,1.053]],"v":[[16.381,-35.954],[0,-39.5],[-38.514,-8.811]],"c":false}]},{"i":{"x":0.667,"y":1},"o":{"x":0.167,"y":0},"t":114,"s":[{"i":[[13.07,5.995],[5.81,0.629],[5.365,-12.351]],"o":[[-4.782,-2.194],[-18.677,-2.022],[-0.321,0.74]],"v":[[18.741,-17.799],[2.734,-22.142],[-37.973,-3.967]],"c":false}]},{"i":{"x":0.833,"y":0.833},"o":{"x":0.167,"y":0},"t":140,"s":[{"i":[[13.07,5.995],[5.81,0.629],[5.365,-12.351]],"o":[[-4.782,-2.194],[-18.677,-2.022],[-0.321,0.74]],"v":[[18.741,-17.799],[2.734,-22.142],[-37.973,-3.967]],"c":false}]},{"i":{"x":0.833,"y":0.833},"o":{"x":0.167,"y":0.167},"t":158,"s":[{"i":[[12.021,7.891],[5.649,1.495],[7.159,-11.405]],"o":[[-4.398,-2.887],[-18.161,-4.805],[-0.429,0.683]],"v":[[23.801,-15.061],[8.628,-21.76],[-34.347,-9.907]],"c":false}]},{"i":{"x":0.667,"y":1},"o":{"x":0.167,"y":0.167},"t":184,"s":[{"i":[[12.021,7.891],[5.649,1.495],[7.159,-11.405]],"o":[[-4.398,-2.887],[-18.161,-4.805],[-0.429,0.683]],"v":[[23.801,-15.061],[8.628,-21.76],[-34.347,-9.907]],"c":false}]},{"t":199,"s":[{"i":[[13.07,5.995],[5.81,0.629],[5.365,-12.351]],"o":[[-4.782,-2.194],[-18.677,-2.022],[-0.321,0.74]],"v":[[18.741,-17.799],[2.734,-22.142],[-37.973,-3.967]],"c":false}]}]},"nm":"Path 1","hd":false},{"ty":"st","c":{"a":0,"k":[0.244577205882,0.244577205882,0.244577205882,1]},"o":{"a":0,"k":100},"w":{"a":0,"k":5},"lc":2,"lj":2,"bm":0,"nm":"Stroke 1","hd":false},{"ty":"tr","p":{"a":0,"k":[0,0]},"a":{"a":0,"k":[0,0]},"s":{"a":0,"k":[100,100]},"r":{"a":0,"k":0},"o":{"a":0,"k":100},"sk":{"a":0,"k":0},"sa":{"a":0,"k":0},"nm":"Transform"}],"nm":"Group 1","bm":0,"hd":false}],"ip":60,"op":240,"st":60,"bm":0},{"ddd":0,"ind":7,"ty":4,"nm":"lupa1","parent":12,"sr":1,"ks":{"r":{"a":1,"k":[{"i":{"x":[0.833],"y":[1]},"o":{"x":[0.167],"y":[0]},"t":140,"s":[-10.978]},{"i":{"x":[0.833],"y":[1]},"o":{"x":[0.167],"y":[0]},"t":158,"s":[39.022]},{"i":{"x":[0.833],"y":[1]},"o":{"x":[0.167],"y":[0]},"t":184,"s":[39.022]},{"t":199,"s":[-10.978]}]},"p":{"a":0,"k":[0,-74.75,0]}},"ao":0,"shapes":[{"ty":"gr","it":[{"ind":0,"ty":"sh","ks":{"a":1,"k":[{"i":{"x":0.667,"y":1},"o":{"x":0.333,"y":0},"t":68,"s":[{"i":[[17.088,-9.328],[13.251,14.849],[-17.088,9.328],[-13.251,-14.849]],"o":[[-17.088,9.328],[-13.251,-14.849],[17.088,-9.328],[13.251,14.849]],"v":[[23.994,35.979],[-30.941,25.983],[-23.994,-17.794],[30.941,-7.798]],"c":true}]},{"i":{"x":0.667,"y":1},"o":{"x":0.333,"y":0},"t":86,"s":[{"i":[[21.12,2.689],[-2.689,21.12],[-21.12,-2.689],[2.689,-21.12]],"o":[[-21.12,-2.689],[2.689,-21.12],[21.12,2.689],[-2.689,21.12]],"v":[[-4.869,38.24],[-38.24,-4.869],[4.869,-38.24],[38.24,4.869]],"c":true}]},{"i":{"x":0.667,"y":1},"o":{"x":0.333,"y":0},"t":100,"s":[{"i":[[21.12,2.689],[-2.689,21.12],[-21.12,-2.689],[2.689,-21.12]],"o":[[-21.12,-2.689],[2.689,-21.12],[21.12,2.689],[-2.689,21.12]],"v":[[-4.869,38.24],[-38.24,-4.869],[4.869,-38.24],[38.24,4.869]],"c":true}]},{"t":114,"s":[{"i":[[17.088,-9.328],[13.251,14.849],[-17.088,9.328],[-13.251,-14.849]],"o":[[-17.088,9.328],[-13.251,-14.849],[17.088,-9.328],[13.251,14.849]],"v":[[23.994,35.979],[-30.941,25.983],[-23.994,-17.794],[30.941,-7.798]],"c":true}]}]},"nm":"Path 1","hd":false},{"ty":"st","c":{"a":0,"k":[0.003921568859,0,0,1]},"o":{"a":0,"k":100},"w":{"a":0,"k":12},"lc":2,"lj":2,"bm":0,"nm":"Stroke 1","hd":false},{"ty":"gf","o":{"a":0,"k":100},"r":1,"bm":0,"g":{"p":3,"k":{"a":0,"k":[0,0.016,0.706,1,0.5,0.016,0.706,1,1,0.016,0.706,1,0,1,0.5,0.5,1,0]}},"s":{"a":0,"k":[-12.358,-89.703]},"e":{"a":0,"k":[42.73,53.2]},"t":1,"nm":"ggg","hd":false},{"ty":"tr","p":{"a":0,"k":[0,0]},"a":{"a":0,"k":[0,0]},"s":{"a":0,"k":[100,100]},"r":{"a":0,"k":0},"o":{"a":0,"k":100},"sk":{"a":0,"k":0},"sa":{"a":0,"k":0},"nm":"Transform"}],"nm":"Group 1","bm":0,"hd":false}],"ip":60,"op":240,"st":60,"bm":0},{"ddd":0,"ind":8,"ty":4,"nm":"lupa14","parent":7,"sr":1,"ks":{"o":{"a":1,"k":[{"t":60,"s":[100],"h":1},{"t":86,"s":[0],"h":1},{"t":100,"s":[100],"h":1}]}},"ao":0,"shapes":[{"ty":"gr","it":[{"ind":0,"ty":"sh","ks":{"a":1,"k":[{"i":{"x":0.667,"y":1},"o":{"x":0.333,"y":0},"t":68,"s":[{"i":[[17.088,-9.328],[13.251,14.849],[-17.088,9.328],[-13.251,-14.849]],"o":[[-17.088,9.328],[-13.251,-14.849],[17.088,-9.328],[13.251,14.849]],"v":[[25.553,28.511],[-29.382,18.515],[-22.434,-25.262],[32.501,-15.266]],"c":true}]},{"i":{"x":0.667,"y":1},"o":{"x":0.333,"y":0},"t":86,"s":[{"i":[[3.495,-21.533],[21.533,3.495],[-3.495,21.533],[-21.533,-3.495]],"o":[[-3.495,21.533],[-21.533,-3.495],[3.495,-21.533],[21.533,3.495]],"v":[[38.99,6.329],[-6.329,38.99],[-38.99,-6.329],[6.329,-38.99]],"c":true}]},{"i":{"x":0.667,"y":1},"o":{"x":0.333,"y":0},"t":100,"s":[{"i":[[3.495,-21.533],[21.533,3.495],[-3.495,21.533],[-21.533,-3.495]],"o":[[-3.495,21.533],[-21.533,-3.495],[3.495,-21.533],[21.533,3.495]],"v":[[38.99,6.329],[-6.329,38.99],[-38.99,-6.329],[6.329,-38.99]],"c":true}]},{"t":114,"s":[{"i":[[17.088,-9.328],[13.251,14.849],[-17.088,9.328],[-13.251,-14.849]],"o":[[-17.088,9.328],[-13.251,-14.849],[17.088,-9.328],[13.251,14.849]],"v":[[25.553,28.511],[-29.382,18.515],[-22.434,-25.262],[32.501,-15.266]],"c":true}]}]},"nm":"Path 1","hd":false},{"ty":"st","c":{"a":0,"k":[0.243137269862,0.243137269862,0.243137269862,1]},"o":{"a":0,"k":100},"w":{"a":0,"k":12},"lc":2,"lj":2,"bm":0,"nm":"Stroke 1","hd":false},{"ty":"tr","p":{"a":0,"k":[0,0]},"a":{"a":0,"k":[0,0]},"s":{"a":0,"k":[100,100]},"r":{"a":0,"k":0},"o":{"a":0,"k":100},"sk":{"a":0,"k":0},"sa":{"a":0,"k":0},"nm":"Transform"}],"nm":"Group 1","bm":0,"hd":false}],"ip":49,"op":260,"st":60,"bm":0},{"ddd":0,"ind":9,"ty":4,"nm":"wing 3","parent":23,"sr":1,"ks":{"p":{"a":0,"k":[-109,126,0]},"a":{"a":0,"k":[-109,126,0]}},"ao":0,"shapes":[{"ty":"gr","it":[{"ind":0,"ty":"sh","ks":{"a":1,"k":[{"i":{"x":0.833,"y":0.833},"o":{"x":0.333,"y":0},"t":140,"s":[{"i":[[23.514,18.753],[24.791,4.094],[-39.056,-4.558]],"o":[[-8.57,-6.834],[-24.791,-4.094],[62.844,7.333]],"v":[[-34.693,101.169],[-126.76,111.854],[-126.001,184.223]],"c":true}]},{"i":{"x":0.667,"y":1},"o":{"x":0.167,"y":0.167},"t":148,"s":[{"i":[[8.083,21.952],[10.935,-16.697],[-5.517,0.598]],"o":[[-1.217,-3.306],[-13.65,20.843],[15.633,-1.695]],"v":[[-56.947,126.241],[-61.526,149.786],[-101.765,179.92]],"c":true}]},{"i":{"x":0.667,"y":1},"o":{"x":0.333,"y":0},"t":158,"s":[{"i":[[20.57,15.871],[0.101,-10.961],[-23.072,-1.033]],"o":[[-11.413,-8.805],[-0.18,19.565],[23.072,1.033]],"v":[[-102.702,123.793],[-156.142,126.079],[-115.249,179.484]],"c":true}]},{"i":{"x":0.833,"y":0.833},"o":{"x":0.333,"y":0},"t":184,"s":[{"i":[[20.57,15.871],[0.101,-10.961],[-23.072,-1.033]],"o":[[-11.413,-8.805],[-0.18,19.565],[23.072,1.033]],"v":[[-102.702,123.793],[-156.142,126.079],[-115.249,179.484]],"c":true}]},{"t":196,"s":[{"i":[[20.4,26.348],[8.292,-10.268],[-5.517,0.598]],"o":[[-2.157,-2.786],[-15.654,19.383],[15.633,-1.695]],"v":[[-59.517,124.902],[-59.17,148.513],[-100.178,169.244]],"c":true}]}]},"nm":"Path 1","hd":false},{"ty":"st","c":{"a":0,"k":[0.533333333333,0.737254901961,0.870588235294,1]},"o":{"a":0,"k":100},"w":{"a":0,"k":10},"lc":2,"lj":2,"bm":0,"nm":"Stroke 1","hd":false},{"ty":"fl","c":{"a":0,"k":[0.788235353956,0.949019667682,0.992156922583,1]},"o":{"a":0,"k":100},"r":1,"bm":0,"nm":"Fill 1","hd":false},{"ty":"tr","p":{"a":0,"k":[0,0]},"a":{"a":0,"k":[0,0]},"s":{"a":0,"k":[100,100]},"r":{"a":0,"k":0},"o":{"a":0,"k":100},"sk":{"a":0,"k":0},"sa":{"a":0,"k":0},"nm":"Transform"}],"nm":"Group 2","bm":0,"hd":false}],"ip":148,"op":197,"st":0,"bm":0},{"ddd":0,"ind":10,"ty":4,"nm":"lupa13","parent":12,"sr":1,"ks":{"r":{"a":0,"k":93.575},"p":{"a":0,"k":[-1.712,7.87,0]},"s":{"a":0,"k":[73.91,47.016,100]}},"ao":0,"shapes":[{"ty":"gr","it":[{"ind":0,"ty":"sh","ks":{"a":1,"k":[{"i":{"x":0.667,"y":1},"o":{"x":0.333,"y":0},"t":68,"s":[{"i":[[8.996,-2.333],[0.06,-2.922],[-4.267,-1.353]],"o":[[-4.333,1.124],[-0.073,3.546],[7.298,2.313]],"v":[[-9.658,-7.785],[-27.093,0.11],[-8.919,8.681]],"c":true}]},{"i":{"x":0.667,"y":1},"o":{"x":0.333,"y":0},"t":86,"s":[{"i":[[8.996,-2.333],[0.06,-2.922],[-4.267,-1.353]],"o":[[-4.333,1.124],[-0.073,3.546],[7.298,2.313]],"v":[[-0.326,-7.284],[-17.761,0.611],[0.413,9.182]],"c":true}]},{"i":{"x":0.667,"y":1},"o":{"x":0.333,"y":0},"t":184,"s":[{"i":[[8.996,-2.333],[0.06,-2.922],[-4.267,-1.353]],"o":[[-4.333,1.124],[-0.073,3.546],[7.298,2.313]],"v":[[-0.326,-7.284],[-17.761,0.611],[0.413,9.182]],"c":true}]},{"t":199,"s":[{"i":[[8.996,-2.333],[0.06,-2.922],[-4.267,-1.353]],"o":[[-4.333,1.124],[-0.073,3.546],[7.298,2.313]],"v":[[-9.658,-7.785],[-27.093,0.11],[-8.919,8.681]],"c":true}]}]},"nm":"Path 1","hd":false},{"ty":"fl","c":{"a":0,"k":[0.243137269862,0.243137269862,0.243137269862,1]},"o":{"a":0,"k":100},"r":1,"bm":0,"nm":"Fill 1","hd":false},{"ty":"tr","p":{"a":0,"k":[0,0]},"a":{"a":0,"k":[0,0]},"s":{"a":0,"k":[100,100]},"r":{"a":0,"k":0},"o":{"a":0,"k":100},"sk":{"a":0,"k":0},"sa":{"a":0,"k":0},"nm":"Transform"}],"nm":"Group 1","bm":0,"hd":false}],"ip":49,"op":262,"st":60,"bm":0},{"ddd":0,"ind":11,"ty":4,"nm":"lupa9","parent":12,"sr":1,"ks":{"r":{"a":0,"k":-1.786},"p":{"a":0,"k":[-0.764,-24.504,0]},"s":{"a":0,"k":[102.993,97.094,100]}},"ao":0,"shapes":[{"ty":"gr","it":[{"ind":0,"ty":"sh","ks":{"a":0,"k":{"i":[[6.617,0],[0,-6.617],[-6.617,0],[0,6.617]],"o":[[-6.617,0],[0,6.617],[6.617,0],[0,-6.617]],"v":[[0,-9],[-12,0],[0,9],[12,0]],"c":true}},"nm":"Path 1","hd":false},{"ty":"fl","c":{"a":0,"k":[0.003921568859,0,0,1]},"o":{"a":0,"k":100},"r":1,"bm":0,"nm":"Fill 1","hd":false},{"ty":"tr","p":{"a":0,"k":[0,0]},"a":{"a":0,"k":[0,0]},"s":{"a":0,"k":[100,100]},"r":{"a":0,"k":0},"o":{"a":0,"k":100},"sk":{"a":0,"k":0},"sa":{"a":0,"k":0},"nm":"Transform"}],"nm":"Group 1","bm":0,"hd":false}],"ip":49,"op":262,"st":60,"bm":0},{"ddd":0,"ind":12,"ty":4,"nm":"lupa3","parent":22,"sr":1,"ks":{"r":{"a":1,"k":[{"i":{"x":[0.667],"y":[1]},"o":{"x":[0.333],"y":[0]},"t":68,"s":[-393.494]},{"t":86,"s":[-360.209],"h":1},{"i":{"x":[0.667],"y":[1]},"o":{"x":[0.333],"y":[0]},"t":105,"s":[-360.209]},{"t":119,"s":[-397.201],"h":1},{"i":{"x":[0.667],"y":[1]},"o":{"x":[0.333],"y":[0]},"t":140,"s":[-397.201]},{"i":{"x":[0.667],"y":[1]},"o":{"x":[0.333],"y":[0]},"t":158,"s":[-401.69]},{"i":{"x":[0.667],"y":[1]},"o":{"x":[0.333],"y":[0]},"t":184,"s":[-401.69]},{"t":199,"s":[-393.494]}]},"p":{"a":1,"k":[{"i":{"x":0.667,"y":1},"o":{"x":0.333,"y":0},"t":68,"s":[104.319,85.197,0],"to":[0,0,0],"ti":[-8.405,-7.521,0]},{"t":86,"s":[125.459,102.881,0],"h":1},{"i":{"x":0.667,"y":1},"o":{"x":0.333,"y":0},"t":105,"s":[125.459,102.881,0],"to":[0,0,0],"ti":[-3.772,8.401,0]},{"t":119,"s":[138.384,46.463,0],"h":1},{"i":{"x":0.667,"y":1},"o":{"x":0.333,"y":0},"t":140,"s":[138.384,46.463,0],"to":[0,0,0],"ti":[0,0,0]},{"i":{"x":0.667,"y":0.667},"o":{"x":0.333,"y":0.333},"t":158,"s":[25.795,60.634,0],"to":[0,0,0],"ti":[0,0,0]},{"i":{"x":0.667,"y":1},"o":{"x":0.333,"y":0},"t":184,"s":[25.795,60.634,0],"to":[0,0,0],"ti":[0,0,0]},{"t":199,"s":[104.319,85.197,0]}]},"s":{"a":0,"k":[133,133,100]}},"ao":0,"shapes":[{"ty":"gr","it":[{"ind":0,"ty":"sh","ks":{"a":1,"k":[{"i":{"x":0.667,"y":1},"o":{"x":0.333,"y":0},"t":68,"s":[{"i":[[2.537,0],[0,-2.268],[-7.11,0],[0,7.111]],"o":[[-2.537,0],[0,7.111],[7.11,0],[0,-2.268]],"v":[[-0.87,-33.465],[-12.098,5.827],[0.797,18.722],[13.691,5.827]],"c":true}]},{"i":{"x":0.667,"y":1},"o":{"x":0.333,"y":0},"t":86,"s":[{"i":[[2.537,0],[0,-2.268],[-7.11,0],[0,7.111]],"o":[[-2.537,0],[0,7.111],[7.11,0],[0,-2.268]],"v":[[0,-26],[-12.894,13.105],[0,26],[12.894,13.105]],"c":true}]},{"i":{"x":0.667,"y":1},"o":{"x":0.333,"y":0},"t":184,"s":[{"i":[[2.537,0],[0,-2.268],[-7.11,0],[0,7.111]],"o":[[-2.537,0],[0,7.111],[7.11,0],[0,-2.268]],"v":[[0,-26],[-12.894,13.105],[0,26],[12.894,13.105]],"c":true}]},{"t":199,"s":[{"i":[[2.537,0],[0,-2.268],[-7.11,0],[0,7.111]],"o":[[-2.537,0],[0,7.111],[7.11,0],[0,-2.268]],"v":[[-0.87,-33.465],[-12.098,5.827],[0.797,18.722],[13.691,5.827]],"c":true}]}]},"nm":"Path 1","hd":false},{"ty":"fl","c":{"a":0,"k":[0.003921568859,0,0,1]},"o":{"a":0,"k":100},"r":1,"bm":0,"nm":"Fill 1","hd":false},{"ty":"tr","p":{"a":0,"k":[0,0]},"a":{"a":0,"k":[0,0]},"s":{"a":0,"k":[100,100]},"r":{"a":0,"k":0},"o":{"a":0,"k":100},"sk":{"a":0,"k":0},"sa":{"a":0,"k":0},"nm":"Transform"}],"nm":"Group 1","bm":0,"hd":false}],"ip":60,"op":244,"st":60,"bm":0},{"ddd":0,"ind":13,"ty":4,"nm":"beak","parent":19,"sr":1,"ks":{"r":{"a":1,"k":[{"i":{"x":[0.667],"y":[1]},"o":{"x":[0.333],"y":[0]},"t":68,"s":[0]},{"i":{"x":[0.667],"y":[1]},"o":{"x":[0.333],"y":[0]},"t":80,"s":[7.15]},{"i":{"x":[0.667],"y":[1]},"o":{"x":[0.333],"y":[0]},"t":105,"s":[2.15]},{"i":{"x":[0.667],"y":[1]},"o":{"x":[0.333],"y":[0]},"t":119,"s":[4]},{"i":{"x":[0.667],"y":[1]},"o":{"x":[0.333],"y":[0]},"t":140,"s":[4]},{"i":{"x":[0.667],"y":[1]},"o":{"x":[0.333],"y":[0]},"t":158,"s":[0]},{"i":{"x":[0.667],"y":[1]},"o":{"x":[0.333],"y":[0]},"t":184,"s":[0]},{"t":200,"s":[0]}]},"p":{"a":1,"k":[{"i":{"x":0.667,"y":1},"o":{"x":0.333,"y":0},"t":68,"s":[-12.915,31.417,0],"to":[0,0,0],"ti":[0,0,0]},{"i":{"x":0.667,"y":0.667},"o":{"x":0.333,"y":0.333},"t":80,"s":[-41.833,18.884,0],"to":[0,0,0],"ti":[0,0,0]},{"i":{"x":0.667,"y":1},"o":{"x":0.333,"y":0},"t":105,"s":[-41.833,18.884,0],"to":[0,0,0],"ti":[0,0,0]},{"i":{"x":0.667,"y":0.667},"o":{"x":0.333,"y":0.333},"t":119,"s":[-5.35,0.383,0],"to":[0,0,0],"ti":[0,0,0]},{"i":{"x":0.667,"y":1},"o":{"x":0.333,"y":0},"t":140,"s":[-5.35,0.383,0],"to":[0,0,0],"ti":[0,0,0]},{"i":{"x":0.667,"y":0.667},"o":{"x":0.333,"y":0.333},"t":158,"s":[-104.319,13.791,0],"to":[0,0,0],"ti":[0,0,0]},{"i":{"x":0.667,"y":1},"o":{"x":0.333,"y":0},"t":184,"s":[-104.319,13.791,0],"to":[0,0,0],"ti":[0,0,0]},{"t":200,"s":[-12.915,31.417,0]}]},"a":{"a":0,"k":[-12.915,31.417,0]}},"ao":0,"shapes":[{"ty":"gr","it":[{"ind":0,"ty":"sh","ks":{"a":1,"k":[{"i":{"x":0.667,"y":1},"o":{"x":0.333,"y":0},"t":68,"s":[{"i":[[4.671,-8.942],[6.306,-2.183]],"o":[[-4.671,8.942],[-6.021,2.084]],"v":[[-17.528,19.391],[-33.686,34.898]],"c":false}]},{"i":{"x":0.667,"y":1},"o":{"x":0.333,"y":0},"t":80,"s":[{"i":[[4.671,-8.942],[6.306,-2.183]],"o":[[-4.671,8.942],[-6.021,2.084]],"v":[[-17.528,19.391],[-33.686,34.898]],"c":false}]},{"i":{"x":0.667,"y":1},"o":{"x":0.333,"y":0},"t":105,"s":[{"i":[[4.671,-8.942],[6.306,-2.183]],"o":[[-4.671,8.942],[-6.021,2.084]],"v":[[-17.528,19.391],[-33.686,34.898]],"c":false}]},{"i":{"x":0.667,"y":1},"o":{"x":0.333,"y":0},"t":119,"s":[{"i":[[4.217,-9.164],[6.189,-2.496]],"o":[[-4.217,9.164],[-5.909,2.383]],"v":[[-15.624,19.69],[-30.985,35.987]],"c":false}]},{"i":{"x":0.667,"y":1},"o":{"x":0.333,"y":0},"t":140,"s":[{"i":[[4.217,-9.164],[6.189,-2.496]],"o":[[-4.217,9.164],[-5.909,2.383]],"v":[[-15.624,19.69],[-30.985,35.987]],"c":false}]},{"i":{"x":0.667,"y":1},"o":{"x":0.333,"y":0},"t":158,"s":[{"i":[[5.586,-8.401],[6.501,-1.508]],"o":[[-5.586,8.401],[-6.207,1.439]],"v":[[-22.411,20.508],[-40.111,34.229]],"c":false}]},{"i":{"x":0.667,"y":1},"o":{"x":0.333,"y":0},"t":184,"s":[{"i":[[5.586,-8.401],[6.501,-1.508]],"o":[[-5.586,8.401],[-6.207,1.439]],"v":[[-22.411,20.508],[-40.111,34.229]],"c":false}]},{"t":200,"s":[{"i":[[4.671,-8.942],[6.306,-2.183]],"o":[[-4.671,8.942],[-6.021,2.084]],"v":[[-17.528,19.391],[-33.686,34.898]],"c":false}]}]},"nm":"Path 1","hd":false},{"ty":"st","c":{"a":0,"k":[1,1,1,1]},"o":{"a":0,"k":100},"w":{"a":0,"k":8},"lc":2,"lj":2,"bm":0,"nm":"Stroke 1","hd":false},{"ty":"tm","s":{"a":0,"k":19.259},"e":{"a":0,"k":98.519},"o":{"a":0,"k":0},"m":1,"nm":"Trim Paths 1","hd":false},{"ty":"tr","p":{"a":0,"k":[0,0]},"a":{"a":0,"k":[0,0]},"s":{"a":0,"k":[100,100]},"r":{"a":0,"k":0},"o":{"a":0,"k":33},"sk":{"a":0,"k":0},"sa":{"a":0,"k":0},"nm":"Transform"}],"nm":"Group 1","bm":0,"hd":false},{"ty":"gr","it":[{"ind":0,"ty":"sh","ks":{"a":1,"k":[{"i":{"x":0.667,"y":1},"o":{"x":0.333,"y":0},"t":68,"s":[{"i":[[-15.92,-6.457],[-17.101,11.594]],"o":[[15.92,6.457],[21.41,-14.515]],"v":[[-47.849,48.917],[21.89,45.908]],"c":false}]},{"i":{"x":0.667,"y":1},"o":{"x":0.333,"y":0},"t":80,"s":[{"i":[[-15.306,-10.557],[-16.447,11.455]],"o":[[15.306,10.557],[22.973,-16]],"v":[[-49.604,53.066],[28.346,50.534]],"c":false}]},{"i":{"x":0.667,"y":1},"o":{"x":0.333,"y":0},"t":105,"s":[{"i":[[-15.306,-10.557],[-16.447,11.455]],"o":[[15.306,10.557],[22.973,-16]],"v":[[-49.604,53.066],[28.346,50.534]],"c":false}]},{"i":{"x":0.667,"y":1},"o":{"x":0.333,"y":0},"t":119,"s":[{"i":[[-18.58,-0.714],[-18.547,7.906]],"o":[[20.701,0.795],[25.754,-10.978]],"v":[[-33.118,48.238],[30.519,38.808]],"c":false}]},{"i":{"x":0.667,"y":1},"o":{"x":0.333,"y":0},"t":140,"s":[{"i":[[-18.58,-0.714],[-18.547,7.906]],"o":[[20.701,0.795],[25.754,-10.978]],"v":[[-33.118,48.238],[30.519,38.808]],"c":false}]},{"i":{"x":0.667,"y":1},"o":{"x":0.333,"y":0},"t":158,"s":[{"i":[[-11.036,-9.243],[-19.383,2.714]],"o":[[10.344,8.664],[21.56,-3.019]],"v":[[-67.597,44.806],[-3.083,58.563]],"c":false}]},{"i":{"x":0.667,"y":1},"o":{"x":0.333,"y":0},"t":184,"s":[{"i":[[-11.036,-9.243],[-19.383,2.714]],"o":[[10.344,8.664],[21.56,-3.019]],"v":[[-67.597,44.806],[-3.083,58.563]],"c":false}]},{"t":200,"s":[{"i":[[-15.92,-6.457],[-17.101,11.594]],"o":[[15.92,6.457],[21.41,-14.515]],"v":[[-47.849,48.917],[21.89,45.908]],"c":false}]}]},"nm":"Path 1","hd":false},{"ty":"st","c":{"a":0,"k":[0.490196079016,0.035294119269,0.035294119269,1]},"o":{"a":0,"k":100},"w":{"a":0,"k":8},"lc":2,"lj":2,"bm":0,"nm":"Stroke 1","hd":false},{"ty":"tr","p":{"a":0,"k":[0,0]},"a":{"a":0,"k":[0,0]},"s":{"a":0,"k":[100,100]},"r":{"a":0,"k":0},"o":{"a":0,"k":100},"sk":{"a":0,"k":0},"sa":{"a":0,"k":0},"nm":"Transform"}],"nm":"Group 2","bm":0,"hd":false},{"ty":"gr","it":[{"ind":0,"ty":"sh","ks":{"a":1,"k":[{"i":{"x":0.667,"y":1},"o":{"x":0.333,"y":0},"t":68,"s":[{"i":[[-1.271,15.228],[-10.654,5.625],[-13.947,0.286],[-9.835,-8.372],[-0.797,-5.957],[31.552,-0.32]],"o":[[0.784,-9.387],[13.435,-7.093],[13.822,-0.283],[7.959,6.775],[1.054,7.874],[-24.054,0.244]],"v":[[-62.877,41.75],[-34.815,26.539],[-12.603,2.992],[8.839,29.089],[24.918,46.086],[-18.368,59.833]],"c":true}]},{"i":{"x":0.667,"y":1},"o":{"x":0.333,"y":0},"t":80,"s":[{"i":[[-2.125,11.881],[-10.654,5.625],[-13.947,0.286],[-9.835,-8.372],[-1.354,-5.855],[31.552,-0.32]],"o":[[1.658,-9.273],[13.435,-7.093],[13.822,-0.283],[7.959,6.775],[3.027,13.091],[-24.054,0.244]],"v":[[-59.57,42.25],[-34.815,26.539],[-12.603,2.992],[10.424,25.627],[36.281,41.3],[-18.25,62.417]],"c":true}]},{"i":{"x":0.667,"y":1},"o":{"x":0.333,"y":0},"t":105,"s":[{"i":[[-2.125,11.881],[-10.654,5.625],[-13.947,0.286],[-9.835,-8.372],[-1.354,-5.855],[31.552,-0.32]],"o":[[1.658,-9.273],[13.435,-7.093],[13.822,-0.283],[7.959,6.775],[3.027,13.091],[-24.054,0.244]],"v":[[-59.57,42.25],[-34.815,26.539],[-12.603,2.992],[10.424,25.627],[36.281,41.3],[-18.25,62.417]],"c":true}]},{"i":{"x":0.667,"y":1},"o":{"x":0.333,"y":0},"t":119,"s":[{"i":[[-0.508,15.272],[-10.359,6.151],[-13.916,0.983],[-10.242,-7.87],[-0.62,-5.978],[31.496,-1.899]],"o":[[0.313,-9.414],[13.063,-7.757],[13.791,-0.975],[8.289,6.369],[1.387,13.364],[-24.011,1.448]],"v":[[-59.797,44.29],[-32.532,27.694],[-11.526,3.065],[12.605,24.519],[39.921,36.921],[-14.439,60.124]],"c":true}]},{"i":{"x":0.667,"y":1},"o":{"x":0.333,"y":0},"t":140,"s":[{"i":[[-0.508,15.272],[-10.359,6.151],[-13.916,0.983],[-10.242,-7.87],[-0.62,-5.978],[31.496,-1.899]],"o":[[0.313,-9.414],[13.063,-7.757],[13.791,-0.975],[8.289,6.369],[1.387,13.364],[-24.011,1.448]],"v":[[-59.797,44.29],[-32.532,27.694],[-11.526,3.065],[12.605,24.519],[39.921,36.921],[-14.439,60.124]],"c":true}]},{"i":{"x":0.667,"y":1},"o":{"x":0.333,"y":0},"t":158,"s":[{"i":[[-2.866,15.01],[-11.187,4.473],[-13.9,-1.183],[-8.9,-9.361],[0.313,-6.002],[31.411,3.001]],"o":[[1.767,-9.252],[14.107,-5.64],[13.775,1.173],[7.202,7.575],[-0.7,13.418],[-23.946,-2.288]],"v":[[-67.861,37.969],[-41.11,25.9],[-15.034,4.635],[6.729,29.648],[26.565,48.744],[-29.365,65.241]],"c":true}]},{"i":{"x":0.667,"y":1},"o":{"x":0.333,"y":0},"t":184,"s":[{"i":[[-2.866,15.01],[-11.187,4.473],[-13.9,-1.183],[-8.9,-9.361],[0.313,-6.002],[31.411,3.001]],"o":[[1.767,-9.252],[14.107,-5.64],[13.775,1.173],[7.202,7.575],[-0.7,13.418],[-23.946,-2.288]],"v":[[-67.861,37.969],[-41.11,25.9],[-15.034,4.635],[6.729,29.648],[26.565,48.744],[-29.365,65.241]],"c":true}]},{"t":200,"s":[{"i":[[-1.271,15.228],[-10.654,5.625],[-13.947,0.286],[-9.835,-8.372],[-0.797,-5.957],[31.552,-0.32]],"o":[[0.784,-9.387],[13.435,-7.093],[13.822,-0.283],[7.959,6.775],[1.054,7.874],[-24.054,0.244]],"v":[[-62.877,41.75],[-34.815,26.539],[-12.603,2.992],[8.839,29.089],[24.918,46.086],[-18.368,59.833]],"c":true}]}]},"nm":"Path 1","hd":false},{"ty":"st","c":{"a":0,"k":[0.811764717102,0.207843139768,0.007843137719,1]},"o":{"a":0,"k":100},"w":{"a":0,"k":8},"lc":2,"lj":2,"bm":0,"nm":"Stroke 1","hd":false},{"ty":"fl","c":{"a":0,"k":[1,0.364705890417,0.121568627656,1]},"o":{"a":0,"k":100},"r":1,"bm":0,"nm":"Fill 1","hd":false},{"ty":"tr","p":{"a":0,"k":[0,0]},"a":{"a":0,"k":[0,0]},"s":{"a":0,"k":[100,100]},"r":{"a":0,"k":0},"o":{"a":0,"k":100},"sk":{"a":0,"k":0},"sa":{"a":0,"k":0},"nm":"Transform"}],"nm":"Group 3","bm":0,"hd":false}],"ip":0,"op":300,"st":0,"bm":0},{"ddd":0,"ind":14,"ty":4,"nm":"eye 3","parent":13,"sr":1,"ks":{"r":{"a":1,"k":[{"i":{"x":[0.667],"y":[1]},"o":{"x":[0.333],"y":[0]},"t":68,"s":[0]},{"i":{"x":[0.667],"y":[1]},"o":{"x":[0.333],"y":[0]},"t":80,"s":[12.187]},{"i":{"x":[0.667],"y":[1]},"o":{"x":[0.333],"y":[0]},"t":100,"s":[12.187]},{"t":114,"s":[0]}]},"p":{"a":1,"k":[{"i":{"x":0.667,"y":1},"o":{"x":0.333,"y":0},"t":68,"s":[43.312,-3.323,0],"to":[0,0,0],"ti":[0,0,0]},{"i":{"x":0.667,"y":0.667},"o":{"x":0.333,"y":0.333},"t":80,"s":[49.804,0.784,0],"to":[0,0,0],"ti":[0,0,0]},{"i":{"x":0.667,"y":1},"o":{"x":0.333,"y":0},"t":100,"s":[49.804,0.784,0],"to":[0,0,0],"ti":[0,0,0]},{"i":{"x":0.667,"y":0.667},"o":{"x":0.333,"y":0.333},"t":114,"s":[48.31,-3.201,0],"to":[0,0,0],"ti":[0,0,0]},{"i":{"x":0.667,"y":1},"o":{"x":0.333,"y":0},"t":140,"s":[48.31,-3.201,0],"to":[0,0,0],"ti":[0,0,0]},{"i":{"x":0.667,"y":0.667},"o":{"x":0.333,"y":0.333},"t":158,"s":[54.79,-3.541,0],"to":[0,0,0],"ti":[0,0,0]},{"i":{"x":0.667,"y":1},"o":{"x":0.333,"y":0},"t":184,"s":[54.79,-3.541,0],"to":[0,0,0],"ti":[0,0,0]},{"t":200,"s":[48.31,-3.201,0]}]},"a":{"a":0,"k":[-87.19,4.299,0]},"s":{"a":1,"k":[{"i":{"x":[0.667,0.667,0.667],"y":[1,1,1]},"o":{"x":[0.333,0.333,0.333],"y":[0,0,0]},"t":68,"s":[-112,140,100]},{"i":{"x":[0.667,0.667,0.667],"y":[1,1,1]},"o":{"x":[0.333,0.333,0.333],"y":[0,0,0]},"t":80,"s":[-90,100,100]},{"i":{"x":[0.667,0.667,0.667],"y":[1,1,1]},"o":{"x":[0.333,0.333,0.333],"y":[0,0,0]},"t":100,"s":[-90,100,100]},{"i":{"x":[0.667,0.667,0.667],"y":[1,1,1]},"o":{"x":[0.333,0.333,0.333],"y":[0,0,0]},"t":114,"s":[-120,150,100]},{"i":{"x":[0.667,0.667,0.667],"y":[1,1,1]},"o":{"x":[0.333,0.333,0.333],"y":[0,0,0]},"t":140,"s":[-120,150,100]},{"i":{"x":[0.667,0.667,0.667],"y":[1,1,1]},"o":{"x":[0.333,0.333,0.333],"y":[0,0,0]},"t":158,"s":[-150,150,100]},{"i":{"x":[0.667,0.667,0.667],"y":[1,1,1]},"o":{"x":[0.333,0.333,0.333],"y":[0,0,0]},"t":184,"s":[-150,150,100]},{"t":200,"s":[-120,150,100]}]}},"ao":0,"shapes":[{"ty":"gr","it":[{"ind":0,"ty":"sh","ks":{"a":1,"k":[{"i":{"x":0.833,"y":1},"o":{"x":0.333,"y":0},"t":68,"s":[{"i":[[5.286,-14.74],[17.618,2.146],[-4.219,15.928],[-14.23,-4.415]],"o":[[-5.286,14.74],[-17.618,-2.146],[4.219,-15.928],[14.23,4.415]],"v":[[-63.129,12.141],[-101.774,32.68],[-126.035,-0.046],[-84.166,-20.304]],"c":true}]},{"i":{"x":0.833,"y":1},"o":{"x":0.333,"y":0},"t":80,"s":[{"i":[[5.286,-14.74],[14.23,4.415],[-5.286,14.74],[-14.23,-4.415]],"o":[[-5.286,14.74],[-14.23,-4.415],[5.286,-14.74],[14.23,4.415]],"v":[[-63.129,12.141],[-98.465,30.835],[-114.659,-3.848],[-79.322,-22.542]],"c":true}]},{"i":{"x":0.833,"y":1},"o":{"x":0.333,"y":0},"t":103,"s":[{"i":[[5.286,-14.74],[14.23,4.415],[-5.286,14.74],[-14.23,-4.415]],"o":[[-5.286,14.74],[-14.23,-4.415],[5.286,-14.74],[14.23,4.415]],"v":[[-63.129,12.141],[-98.465,30.835],[-114.659,-3.848],[-79.322,-22.542]],"c":true}]},{"i":{"x":0.833,"y":1},"o":{"x":0.333,"y":0},"t":109,"s":[{"i":[[1.018,-1.165],[14.097,0.064],[-1.018,1.165],[-14.097,-0.064]],"o":[[-1.018,1.165],[-14.097,-0.064],[1.018,-1.165],[14.097,0.064]],"v":[[-61.665,4.415],[-90.126,10.17],[-112.714,4.183],[-86.441,5.951]],"c":true}]},{"i":{"x":0.667,"y":1},"o":{"x":0.333,"y":0},"t":116,"s":[{"i":[[0,-9.35],[14.097,0.888],[-1.018,16.156],[-14.097,-0.888]],"o":[[0,16.188],[-14.097,-0.888],[1.018,-16.156],[14.097,0.888]],"v":[[-61.665,5.907],[-89.032,33.552],[-112.714,2.691],[-86.052,-16.433]],"c":true}]},{"i":{"x":0.833,"y":1},"o":{"x":0.333,"y":0},"t":142,"s":[{"i":[[1.018,-16.156],[14.097,0.888],[-1.018,16.156],[-14.097,-0.888]],"o":[[-1.018,16.156],[-14.097,-0.888],[1.018,-16.156],[14.097,0.888]],"v":[[-61.665,5.907],[-89.032,33.552],[-112.714,2.691],[-85.347,-24.953]],"c":true}]},{"i":{"x":0.667,"y":1},"o":{"x":0.333,"y":0},"t":148,"s":[{"i":[[1.018,-1.165],[14.097,0.064],[-1.018,1.165],[-14.097,-0.064]],"o":[[-1.018,1.165],[-14.097,-0.064],[1.018,-1.165],[14.097,0.064]],"v":[[-61.665,4.415],[-90.126,10.17],[-112.714,4.183],[-86.441,5.951]],"c":true}]},{"i":{"x":0.667,"y":1},"o":{"x":0.333,"y":0},"t":155,"s":[{"i":[[-6.698,-5.469],[17.027,1.075],[-1.439,16.125],[-17.027,-1.075]],"o":[[-0.342,12.83],[-17.027,-1.075],[6.603,-8.073],[17.027,1.075]],"v":[[-53.728,6.92],[-84.989,33.901],[-112.282,-1.102],[-83.899,-12.222]],"c":true}]},{"i":{"x":0.833,"y":1},"o":{"x":0.333,"y":0},"t":184,"s":[{"i":[[-6.698,-5.469],[17.027,1.075],[-1.439,16.125],[-17.027,-1.075]],"o":[[-0.342,12.83],[-17.027,-1.075],[6.603,-8.073],[17.027,1.075]],"v":[[-53.728,6.92],[-84.989,33.901],[-112.282,-1.102],[-83.899,-12.222]],"c":true}]},{"i":{"x":0.833,"y":1},"o":{"x":0.333,"y":0},"t":190,"s":[{"i":[[1.018,-1.165],[14.097,0.064],[-1.018,1.165],[-14.097,-0.064]],"o":[[-1.018,1.165],[-14.097,-0.064],[1.018,-1.165],[14.097,0.064]],"v":[[-61.665,4.415],[-90.126,10.17],[-112.714,4.183],[-86.441,5.951]],"c":true}]},{"i":{"x":0.833,"y":1},"o":{"x":0.333,"y":0},"t":196,"s":[{"i":[[0,-9.35],[14.097,0.888],[-1.018,16.156],[-14.097,-0.888]],"o":[[0,16.188],[-14.097,-0.888],[1.018,-16.156],[14.097,0.888]],"v":[[-61.665,5.907],[-89.032,33.552],[-112.714,2.691],[-86.052,-16.433]],"c":true}]},{"i":{"x":0.833,"y":1},"o":{"x":0.333,"y":0},"t":211,"s":[{"i":[[0,-9.35],[14.097,0.888],[-1.018,16.156],[-14.097,-0.888]],"o":[[0,16.188],[-14.097,-0.888],[1.018,-16.156],[14.097,0.888]],"v":[[-61.665,5.907],[-89.032,33.552],[-112.714,2.691],[-86.052,-16.433]],"c":true}]},{"i":{"x":0.833,"y":1},"o":{"x":0.333,"y":0},"t":217,"s":[{"i":[[1.018,-1.165],[14.097,0.064],[-1.018,1.165],[-14.097,-0.064]],"o":[[-1.018,1.165],[-14.097,-0.064],[1.018,-1.165],[14.097,0.064]],"v":[[-61.665,4.415],[-90.126,10.17],[-112.714,4.183],[-86.441,5.951]],"c":true}]},{"i":{"x":0.833,"y":1},"o":{"x":0.333,"y":0},"t":223,"s":[{"i":[[0,-9.35],[14.097,0.888],[-1.018,16.156],[-14.097,-0.888]],"o":[[0,16.188],[-14.097,-0.888],[1.018,-16.156],[14.097,0.888]],"v":[[-61.665,5.907],[-89.032,33.552],[-112.714,2.691],[-86.052,-16.433]],"c":true}]},{"i":{"x":0.833,"y":1},"o":{"x":0.333,"y":0},"t":226,"s":[{"i":[[0,-9.35],[14.097,0.888],[-1.018,16.156],[-14.097,-0.888]],"o":[[0,16.188],[-14.097,-0.888],[1.018,-16.156],[14.097,0.888]],"v":[[-61.665,5.907],[-89.032,33.552],[-112.714,2.691],[-86.052,-16.433]],"c":true}]},{"i":{"x":0.833,"y":1},"o":{"x":0.333,"y":0},"t":232,"s":[{"i":[[1.018,-1.165],[14.097,0.064],[-1.018,1.165],[-14.097,-0.064]],"o":[[-1.018,1.165],[-14.097,-0.064],[1.018,-1.165],[14.097,0.064]],"v":[[-61.665,4.415],[-90.126,10.17],[-112.714,4.183],[-86.441,5.951]],"c":true}]},{"t":238,"s":[{"i":[[0,-9.35],[14.097,0.888],[-1.018,16.156],[-14.097,-0.888]],"o":[[0,16.188],[-14.097,-0.888],[1.018,-16.156],[14.097,0.888]],"v":[[-61.665,5.907],[-89.032,33.552],[-112.714,2.691],[-86.052,-16.433]],"c":true}]}]},"nm":"Path 1","hd":false},{"ty":"st","c":{"a":0,"k":[0,0,0,1]},"o":{"a":0,"k":100},"w":{"a":1,"k":[{"i":{"x":[0.833],"y":[1]},"o":{"x":[0.333],"y":[0]},"t":68,"s":[0]},{"i":{"x":[0.833],"y":[1]},"o":{"x":[0.333],"y":[0]},"t":80,"s":[0]},{"i":{"x":[0.833],"y":[1]},"o":{"x":[0.333],"y":[0]},"t":103,"s":[0]},{"i":{"x":[0.833],"y":[1]},"o":{"x":[0.333],"y":[0]},"t":109,"s":[10]},{"i":{"x":[0.667],"y":[1]},"o":{"x":[0.333],"y":[0]},"t":116,"s":[0]},{"i":{"x":[0.833],"y":[1]},"o":{"x":[0.333],"y":[0]},"t":142,"s":[0]},{"i":{"x":[0.667],"y":[1]},"o":{"x":[0.333],"y":[0]},"t":148,"s":[10]},{"i":{"x":[0.667],"y":[1]},"o":{"x":[0.333],"y":[0]},"t":155,"s":[0]},{"i":{"x":[0.833],"y":[1]},"o":{"x":[0.333],"y":[0]},"t":184,"s":[0]},{"i":{"x":[0.833],"y":[1]},"o":{"x":[0.333],"y":[0]},"t":190,"s":[10]},{"i":{"x":[0.833],"y":[1]},"o":{"x":[0.333],"y":[0]},"t":196,"s":[0]},{"i":{"x":[0.833],"y":[1]},"o":{"x":[0.333],"y":[0]},"t":211,"s":[0]},{"i":{"x":[0.833],"y":[1]},"o":{"x":[0.333],"y":[0]},"t":217,"s":[10]},{"i":{"x":[0.833],"y":[1]},"o":{"x":[0.333],"y":[0]},"t":223,"s":[0]},{"i":{"x":[0.833],"y":[1]},"o":{"x":[0.333],"y":[0]},"t":226,"s":[0]},{"i":{"x":[0.833],"y":[1]},"o":{"x":[0.333],"y":[0]},"t":232,"s":[10]},{"t":238,"s":[0]}]},"lc":2,"lj":2,"bm":0,"nm":"Stroke 1","hd":false},{"ty":"fl","c":{"a":0,"k":[0.152941176471,0.956862804936,0.933333393172,1]},"o":{"a":0,"k":100},"r":1,"bm":0,"nm":"Fill 1","hd":false},{"ty":"tr","p":{"a":0,"k":[0,0]},"a":{"a":0,"k":[0,0]},"s":{"a":0,"k":[100,100]},"r":{"a":0,"k":0},"o":{"a":0,"k":100},"sk":{"a":0,"k":0},"sa":{"a":0,"k":0},"nm":"Transform"}],"nm":"Group 2","bm":0,"hd":false}],"ip":0,"op":300,"st":0,"bm":0},{"ddd":0,"ind":15,"ty":4,"nm":"eye","parent":13,"sr":1,"ks":{"r":{"a":1,"k":[{"i":{"x":[0.667],"y":[1]},"o":{"x":[0.333],"y":[0]},"t":68,"s":[0]},{"i":{"x":[0.667],"y":[1]},"o":{"x":[0.333],"y":[0]},"t":80,"s":[0]},{"i":{"x":[0.667],"y":[1]},"o":{"x":[0.333],"y":[0]},"t":100,"s":[0]},{"i":{"x":[0.667],"y":[1]},"o":{"x":[0.333],"y":[0]},"t":114,"s":[0]},{"i":{"x":[0.667],"y":[1]},"o":{"x":[0.333],"y":[0]},"t":140,"s":[0]},{"i":{"x":[0.667],"y":[1]},"o":{"x":[0.333],"y":[0]},"t":158,"s":[5.287]},{"i":{"x":[0.667],"y":[1]},"o":{"x":[0.333],"y":[0]},"t":184,"s":[5.287]},{"t":200,"s":[0]}]},"p":{"a":1,"k":[{"i":{"x":0.667,"y":0.667},"o":{"x":0.333,"y":0.333},"t":68,"s":[-87.19,4.299,0],"to":[0,0,0],"ti":[0,0,0]},{"i":{"x":0.667,"y":0.667},"o":{"x":0.333,"y":0.333},"t":80,"s":[-87.19,4.299,0],"to":[0,0,0],"ti":[0,0,0]},{"i":{"x":0.667,"y":1},"o":{"x":0.333,"y":0},"t":100,"s":[-87.19,4.299,0],"to":[0,0,0],"ti":[0,0,0]},{"i":{"x":0.667,"y":0.667},"o":{"x":0.333,"y":0.333},"t":114,"s":[-82.064,6.381,0],"to":[0,0,0],"ti":[0,0,0]},{"i":{"x":0.667,"y":1},"o":{"x":0.333,"y":0},"t":140,"s":[-82.064,6.381,0],"to":[0,0,0],"ti":[0,0,0]},{"i":{"x":0.667,"y":0.667},"o":{"x":0.333,"y":0.333},"t":158,"s":[-61.839,1.924,0],"to":[0,0,0],"ti":[0,0,0]},{"i":{"x":0.667,"y":1},"o":{"x":0.333,"y":0},"t":184,"s":[-61.839,1.924,0],"to":[0,0,0],"ti":[0,0,0]},{"t":200,"s":[-87.19,4.299,0]}]},"a":{"a":0,"k":[-87.19,4.299,0]},"s":{"a":1,"k":[{"i":{"x":[0.667,0.667,0.667],"y":[1,1,1]},"o":{"x":[0.333,0.333,0.333],"y":[0,0,0]},"t":68,"s":[100,100,100]},{"i":{"x":[0.667,0.667,0.667],"y":[1,1,1]},"o":{"x":[0.333,0.333,0.333],"y":[0,0,0]},"t":80,"s":[100,100,100]},{"i":{"x":[0.667,0.667,0.667],"y":[1,1,1]},"o":{"x":[0.333,0.333,0.333],"y":[0,0,0]},"t":100,"s":[100,100,100]},{"i":{"x":[0.667,0.667,0.667],"y":[1,1,1]},"o":{"x":[0.333,0.333,0.333],"y":[0,0,0]},"t":114,"s":[100,100,100]},{"i":{"x":[0.667,0.667,0.667],"y":[1,1,1]},"o":{"x":[0.333,0.333,0.333],"y":[0,0,0]},"t":140,"s":[100,100,100]},{"i":{"x":[0.667,0.667,0.667],"y":[1,1,1]},"o":{"x":[0.333,0.333,0.333],"y":[0,0,0]},"t":158,"s":[70,90,100]},{"i":{"x":[0.667,0.667,0.667],"y":[1,1,1]},"o":{"x":[0.333,0.333,0.333],"y":[0,0,0]},"t":184,"s":[70,90,100]},{"t":200,"s":[100,100,100]}]}},"ao":0,"shapes":[{"ty":"gr","it":[{"ind":0,"ty":"sh","ks":{"a":1,"k":[{"i":{"x":0.833,"y":1},"o":{"x":0.333,"y":0},"t":103,"s":[{"i":[[1.018,-16.156],[14.097,0.888],[-1.018,16.156],[-14.097,-0.888]],"o":[[-1.018,16.156],[-14.097,-0.888],[1.018,-16.156],[14.097,0.888]],"v":[[-61.665,5.907],[-89.032,33.552],[-112.714,2.691],[-85.347,-24.953]],"c":true}]},{"i":{"x":0.667,"y":1},"o":{"x":0.333,"y":0},"t":109,"s":[{"i":[[1.018,-1.165],[14.097,0.064],[-1.018,1.165],[-14.097,-0.064]],"o":[[-1.018,1.165],[-14.097,-0.064],[1.018,-1.165],[14.097,0.064]],"v":[[-61.665,4.415],[-90.126,10.17],[-112.714,4.183],[-86.441,5.951]],"c":true}]},{"i":{"x":0.667,"y":1},"o":{"x":0.333,"y":0},"t":116,"s":[{"i":[[1.018,-16.156],[14.097,0.888],[-1.018,16.156],[-14.097,-0.888]],"o":[[-1.018,16.156],[-14.097,-0.888],[1.018,-16.156],[14.097,0.888]],"v":[[-61.665,5.907],[-89.032,33.552],[-112.714,2.691],[-85.347,-24.953]],"c":true}]},{"i":{"x":0.833,"y":1},"o":{"x":0.333,"y":0},"t":142,"s":[{"i":[[1.018,-16.156],[14.097,0.888],[-1.018,16.156],[-14.097,-0.888]],"o":[[-1.018,16.156],[-14.097,-0.888],[1.018,-16.156],[14.097,0.888]],"v":[[-61.665,5.907],[-89.032,33.552],[-112.714,2.691],[-85.347,-24.953]],"c":true}]},{"i":{"x":0.667,"y":1},"o":{"x":0.333,"y":0},"t":148,"s":[{"i":[[1.018,-1.165],[14.097,0.064],[-1.018,1.165],[-14.097,-0.064]],"o":[[-1.018,1.165],[-14.097,-0.064],[1.018,-1.165],[14.097,0.064]],"v":[[-61.665,4.415],[-90.126,10.17],[-112.714,4.183],[-86.441,5.951]],"c":true}]},{"i":{"x":0.667,"y":1},"o":{"x":0.333,"y":0},"t":155,"s":[{"i":[[1.018,-16.156],[14.097,0.888],[-1.018,16.156],[-14.097,-0.888]],"o":[[-1.018,16.156],[-14.097,-0.888],[1.018,-16.156],[14.097,0.888]],"v":[[-61.665,5.907],[-89.032,33.552],[-112.714,2.691],[-85.347,-24.953]],"c":true}]},{"i":{"x":0.833,"y":1},"o":{"x":0.333,"y":0},"t":184,"s":[{"i":[[1.018,-16.156],[14.097,0.888],[-1.018,16.156],[-14.097,-0.888]],"o":[[-1.018,16.156],[-14.097,-0.888],[1.018,-16.156],[14.097,0.888]],"v":[[-61.665,5.907],[-89.032,33.552],[-112.714,2.691],[-85.347,-24.953]],"c":true}]},{"i":{"x":0.667,"y":1},"o":{"x":0.333,"y":0},"t":190,"s":[{"i":[[1.018,-1.165],[14.097,0.064],[-1.018,1.165],[-14.097,-0.064]],"o":[[-1.018,1.165],[-14.097,-0.064],[1.018,-1.165],[14.097,0.064]],"v":[[-61.665,4.415],[-90.126,10.17],[-112.714,4.183],[-86.441,5.951]],"c":true}]},{"i":{"x":0.667,"y":1},"o":{"x":0.167,"y":0},"t":196,"s":[{"i":[[1.018,-16.156],[14.097,0.888],[-1.018,16.156],[-14.097,-0.888]],"o":[[-1.018,16.156],[-14.097,-0.888],[1.018,-16.156],[14.097,0.888]],"v":[[-61.665,5.907],[-89.032,33.552],[-112.714,2.691],[-85.347,-24.953]],"c":true}]},{"i":{"x":0.833,"y":1},"o":{"x":0.333,"y":0},"t":211,"s":[{"i":[[1.018,-16.156],[14.097,0.888],[-1.018,16.156],[-14.097,-0.888]],"o":[[-1.018,16.156],[-14.097,-0.888],[1.018,-16.156],[14.097,0.888]],"v":[[-61.665,5.907],[-89.032,33.552],[-112.714,2.691],[-85.347,-24.953]],"c":true}]},{"i":{"x":0.667,"y":1},"o":{"x":0.333,"y":0},"t":217,"s":[{"i":[[1.018,-1.165],[14.097,0.064],[-1.018,1.165],[-14.097,-0.064]],"o":[[-1.018,1.165],[-14.097,-0.064],[1.018,-1.165],[14.097,0.064]],"v":[[-61.665,4.415],[-90.126,10.17],[-112.714,4.183],[-86.441,5.951]],"c":true}]},{"i":{"x":0.667,"y":1},"o":{"x":0.167,"y":0},"t":223,"s":[{"i":[[1.018,-16.156],[14.097,0.888],[-1.018,16.156],[-14.097,-0.888]],"o":[[-1.018,16.156],[-14.097,-0.888],[1.018,-16.156],[14.097,0.888]],"v":[[-61.665,5.907],[-89.032,33.552],[-112.714,2.691],[-85.347,-24.953]],"c":true}]},{"i":{"x":0.833,"y":1},"o":{"x":0.333,"y":0},"t":226,"s":[{"i":[[1.018,-16.156],[14.097,0.888],[-1.018,16.156],[-14.097,-0.888]],"o":[[-1.018,16.156],[-14.097,-0.888],[1.018,-16.156],[14.097,0.888]],"v":[[-61.665,5.907],[-89.032,33.552],[-112.714,2.691],[-85.347,-24.953]],"c":true}]},{"i":{"x":0.667,"y":1},"o":{"x":0.333,"y":0},"t":232,"s":[{"i":[[1.018,-1.165],[14.097,0.064],[-1.018,1.165],[-14.097,-0.064]],"o":[[-1.018,1.165],[-14.097,-0.064],[1.018,-1.165],[14.097,0.064]],"v":[[-61.665,4.415],[-90.126,10.17],[-112.714,4.183],[-86.441,5.951]],"c":true}]},{"t":238,"s":[{"i":[[1.018,-16.156],[14.097,0.888],[-1.018,16.156],[-14.097,-0.888]],"o":[[-1.018,16.156],[-14.097,-0.888],[1.018,-16.156],[14.097,0.888]],"v":[[-61.665,5.907],[-89.032,33.552],[-112.714,2.691],[-85.347,-24.953]],"c":true}]}]},"nm":"Path 1","hd":false},{"ty":"st","c":{"a":0,"k":[0,0,0,1]},"o":{"a":0,"k":100},"w":{"a":1,"k":[{"i":{"x":[0.667],"y":[1]},"o":{"x":[0.333],"y":[0]},"t":103,"s":[0]},{"i":{"x":[0.667],"y":[1]},"o":{"x":[0.333],"y":[0]},"t":109,"s":[10]},{"i":{"x":[0.667],"y":[1]},"o":{"x":[0.333],"y":[0]},"t":116,"s":[0]},{"i":{"x":[0.667],"y":[1]},"o":{"x":[0.333],"y":[0]},"t":142,"s":[0]},{"i":{"x":[0.667],"y":[1]},"o":{"x":[0.333],"y":[0]},"t":148,"s":[10]},{"i":{"x":[0.667],"y":[1]},"o":{"x":[0.333],"y":[0]},"t":155,"s":[0]},{"i":{"x":[0.667],"y":[1]},"o":{"x":[0.333],"y":[0]},"t":184,"s":[0]},{"i":{"x":[0.667],"y":[1]},"o":{"x":[0.333],"y":[0]},"t":190,"s":[10]},{"i":{"x":[0.667],"y":[1]},"o":{"x":[0.167],"y":[0]},"t":196,"s":[0]},{"i":{"x":[0.667],"y":[1]},"o":{"x":[0.333],"y":[0]},"t":211,"s":[0]},{"i":{"x":[0.667],"y":[1]},"o":{"x":[0.333],"y":[0]},"t":217,"s":[10]},{"i":{"x":[0.667],"y":[1]},"o":{"x":[0.167],"y":[0]},"t":223,"s":[0]},{"i":{"x":[0.667],"y":[1]},"o":{"x":[0.333],"y":[0]},"t":226,"s":[0]},{"i":{"x":[0.667],"y":[1]},"o":{"x":[0.333],"y":[0]},"t":232,"s":[10]},{"t":238,"s":[0]}]},"lc":2,"lj":2,"bm":0,"nm":"Stroke 1","hd":false},{"ty":"fl","c":{"a":0,"k":[0.152941176471,0.956862804936,0.933333393172,1]},"o":{"a":0,"k":100},"r":1,"bm":0,"nm":"Fill 1","hd":false},{"ty":"tr","p":{"a":0,"k":[0,0]},"a":{"a":0,"k":[0,0]},"s":{"a":0,"k":[100,100]},"r":{"a":0,"k":0},"o":{"a":0,"k":100},"sk":{"a":0,"k":0},"sa":{"a":0,"k":0},"nm":"Transform"}],"nm":"Group 2","bm":0,"hd":false}],"ip":0,"op":300,"st":0,"bm":0},{"ddd":0,"ind":16,"ty":4,"nm":"bl","parent":19,"sr":1,"ks":{"p":{"a":0,"k":[-52.629,-26.409,0]},"a":{"a":0,"k":[-52.629,-26.409,0]}},"ao":0,"shapes":[{"ty":"gr","it":[{"ind":0,"ty":"sh","ks":{"a":1,"k":[{"i":{"x":0.667,"y":1},"o":{"x":0.333,"y":0},"t":68,"s":[{"i":[[0,0],[5.434,10.152]],"o":[[-2.201,-10.956],[-6.376,-11.912]],"v":[[65.253,-48.412],[53.695,-80.305]],"c":false}]},{"i":{"x":0.667,"y":1},"o":{"x":0.333,"y":0},"t":80,"s":[{"i":[[0,0],[-0.253,11.512]],"o":[[3.465,-10.624],[0.297,-13.507]],"v":[[63.196,2.846],[68.793,-30.612]],"c":false}]},{"i":{"x":0.667,"y":1},"o":{"x":0.333,"y":0},"t":100,"s":[{"i":[[0,0],[-0.253,11.512]],"o":[[3.465,-10.624],[0.297,-13.507]],"v":[[63.196,2.846],[68.793,-30.612]],"c":false}]},{"i":{"x":0.667,"y":1},"o":{"x":0.333,"y":0},"t":114,"s":[{"i":[[0,0],[1.138,18.195]],"o":[[3.465,-10.624],[-0.843,-13.484]],"v":[[67.417,-7.47],[70.729,-47.35]],"c":false}]},{"i":{"x":0.667,"y":1},"o":{"x":0.333,"y":0},"t":140,"s":[{"i":[[0,0],[1.138,18.195]],"o":[[3.465,-10.624],[-0.843,-13.484]],"v":[[67.417,-7.47],[70.729,-47.35]],"c":false}]},{"i":{"x":0.667,"y":1},"o":{"x":0.333,"y":0},"t":158,"s":[{"i":[[0,0],[1.392,7.685]],"o":[[3.465,-10.624],[-2.408,-13.294]],"v":[[67.417,-7.47],[69.733,-37.744]],"c":false}]},{"i":{"x":0.667,"y":1},"o":{"x":0.333,"y":0},"t":184,"s":[{"i":[[0,0],[1.392,7.685]],"o":[[3.465,-10.624],[-2.408,-13.294]],"v":[[67.417,-7.47],[69.733,-37.744]],"c":false}]},{"t":200,"s":[{"i":[[0,0],[5.434,10.152]],"o":[[-2.201,-10.956],[-6.376,-11.912]],"v":[[65.253,-48.412],[53.695,-80.305]],"c":false}]}]},"nm":"Path 1","hd":false},{"ty":"st","c":{"a":0,"k":[1,1,1,1]},"o":{"a":0,"k":100},"w":{"a":0,"k":8},"lc":2,"lj":2,"bm":0,"nm":"Stroke 1","hd":false},{"ty":"tm","s":{"a":1,"k":[{"i":{"x":[0.667],"y":[1]},"o":{"x":[0.333],"y":[0]},"t":60,"s":[20]},{"i":{"x":[0.667],"y":[1]},"o":{"x":[0.333],"y":[0]},"t":72,"s":[10]},{"i":{"x":[0.667],"y":[1]},"o":{"x":[0.333],"y":[0]},"t":84.834,"s":[20]},{"i":{"x":[0.667],"y":[1]},"o":{"x":[0.333],"y":[0]},"t":97.666,"s":[5]},{"i":{"x":[0.667],"y":[1]},"o":{"x":[0.333],"y":[0]},"t":110.5,"s":[10]},{"i":{"x":[0.667],"y":[1]},"o":{"x":[0.333],"y":[0]},"t":123.334,"s":[10]},{"i":{"x":[0.667],"y":[1]},"o":{"x":[0.333],"y":[0]},"t":136.166,"s":[10]},{"i":{"x":[0.667],"y":[1]},"o":{"x":[0.333],"y":[0]},"t":149,"s":[20]},{"i":{"x":[0.667],"y":[1]},"o":{"x":[0.333],"y":[0]},"t":161.834,"s":[5]},{"i":{"x":[0.667],"y":[1]},"o":{"x":[0.333],"y":[0]},"t":174.666,"s":[10]},{"i":{"x":[0.667],"y":[1]},"o":{"x":[0.333],"y":[0]},"t":187.5,"s":[10]},{"i":{"x":[0.667],"y":[1]},"o":{"x":[0.333],"y":[0]},"t":200.334,"s":[20]},{"i":{"x":[0.667],"y":[1]},"o":{"x":[0.333],"y":[0]},"t":213.166,"s":[5]},{"i":{"x":[0.667],"y":[1]},"o":{"x":[0.333],"y":[0]},"t":226,"s":[10]},{"t":240,"s":[20]}]},"e":{"a":1,"k":[{"i":{"x":[0.667],"y":[1]},"o":{"x":[0.333],"y":[0]},"t":60,"s":[100]},{"i":{"x":[0.667],"y":[1]},"o":{"x":[0.333],"y":[0]},"t":72,"s":[80]},{"i":{"x":[0.667],"y":[1]},"o":{"x":[0.333],"y":[0]},"t":84.834,"s":[100]},{"i":{"x":[0.667],"y":[1]},"o":{"x":[0.333],"y":[0]},"t":97.666,"s":[70]},{"i":{"x":[0.667],"y":[1]},"o":{"x":[0.333],"y":[0]},"t":110.5,"s":[90]},{"i":{"x":[0.667],"y":[1]},"o":{"x":[0.333],"y":[0]},"t":123.334,"s":[80]},{"i":{"x":[0.667],"y":[1]},"o":{"x":[0.333],"y":[0]},"t":136.166,"s":[80]},{"i":{"x":[0.667],"y":[1]},"o":{"x":[0.333],"y":[0]},"t":149,"s":[100]},{"i":{"x":[0.667],"y":[1]},"o":{"x":[0.333],"y":[0]},"t":161.834,"s":[70]},{"i":{"x":[0.667],"y":[1]},"o":{"x":[0.333],"y":[0]},"t":174.666,"s":[90]},{"i":{"x":[0.667],"y":[1]},"o":{"x":[0.333],"y":[0]},"t":187.5,"s":[80]},{"i":{"x":[0.667],"y":[1]},"o":{"x":[0.333],"y":[0]},"t":200.334,"s":[100]},{"i":{"x":[0.667],"y":[1]},"o":{"x":[0.333],"y":[0]},"t":213.166,"s":[70]},{"i":{"x":[0.667],"y":[1]},"o":{"x":[0.333],"y":[0]},"t":226,"s":[90]},{"t":240,"s":[100]}]},"o":{"a":0,"k":0},"m":1,"nm":"Trim Paths 1","hd":false},{"ty":"tr","p":{"a":0,"k":[0,0]},"a":{"a":0,"k":[0,0]},"s":{"a":0,"k":[100,100]},"r":{"a":0,"k":0},"o":{"a":0,"k":100},"sk":{"a":0,"k":0},"sa":{"a":0,"k":0},"nm":"Transform"}],"nm":"Group 1","bm":0,"hd":false}],"ip":0,"op":300,"st":0,"bm":0},{"ddd":0,"ind":17,"ty":4,"nm":"eyes 2","parent":13,"sr":1,"ks":{"o":{"a":1,"k":[{"t":60,"s":[100],"h":1},{"t":77,"s":[0],"h":1},{"t":110,"s":[100],"h":1}]},"r":{"a":0,"k":-2.286},"p":{"a":0,"k":[-17.364,0.784,0]},"a":{"a":0,"k":[25.033,1.607,0]},"s":{"a":0,"k":[66,66,100]}},"ao":0,"shapes":[{"ty":"gr","it":[{"ind":0,"ty":"sh","ks":{"a":1,"k":[{"i":{"x":0.833,"y":0.833},"o":{"x":0.333,"y":0},"t":68,"s":[{"i":[[66.634,0.251],[8.973,15.615],[-72.274,22.257]],"o":[[0,0],[-19.138,-33.304],[123.75,19.68]],"v":[[131.485,91.18],[70.333,65.557],[140.022,-56.459]],"c":true}]},{"i":{"x":0.667,"y":1},"o":{"x":0.167,"y":0.167},"t":77,"s":[{"i":[[14.525,0.05],[0,0],[-1.098,-0.324]],"o":[[0,0],[0,0],[12.206,3.608]],"v":[[166.636,24.781],[158.16,24.676],[170.638,-0.319]],"c":true}]},{"i":{"x":0.833,"y":0.833},"o":{"x":0.333,"y":0},"t":105,"s":[{"i":[[14.525,0.05],[0,0],[-1.098,-0.324]],"o":[[0,0],[0,0],[12.206,3.608]],"v":[[174.069,24.871],[165.593,24.766],[178.071,-0.23]],"c":true}]},{"i":{"x":0.667,"y":1},"o":{"x":0.167,"y":0.167},"t":110,"s":[{"i":[[14.525,0.05],[0,0],[-1.098,-0.324]],"o":[[0,0],[0,0],[12.206,3.608]],"v":[[174.069,24.871],[165.593,24.766],[178.071,-0.23]],"c":true}]},{"i":{"x":0.667,"y":1},"o":{"x":0.333,"y":0},"t":119,"s":[{"i":[[57.731,0.218],[7.774,13.528],[-62.617,19.283]],"o":[[0,0],[-16.581,-28.854],[89.931,26.182]],"v":[[139.028,64.958],[83.737,41.299],[138.832,-87.838]],"c":true}]},{"i":{"x":0.667,"y":1},"o":{"x":0.333,"y":0},"t":140,"s":[{"i":[[57.731,0.218],[7.774,13.528],[-62.617,19.283]],"o":[[0,0],[-16.581,-28.854],[89.931,26.182]],"v":[[139.028,64.958],[83.737,41.299],[138.832,-87.838]],"c":true}]},{"i":{"x":0.667,"y":1},"o":{"x":0.333,"y":0},"t":158,"s":[{"i":[[66.1,2.794],[0,0],[-4.979,-1.665]],"o":[[0,0],[0,0],[93.234,31.184]],"v":[[145.455,86.336],[57.081,64.679],[135.74,-42.421]],"c":true}]},{"i":{"x":0.667,"y":1},"o":{"x":0.333,"y":0},"t":184,"s":[{"i":[[66.1,2.794],[0,0],[-4.979,-1.665]],"o":[[0,0],[0,0],[93.234,31.184]],"v":[[145.455,86.336],[57.081,64.679],[135.74,-42.421]],"c":true}]},{"t":200,"s":[{"i":[[66.634,0.251],[8.973,15.615],[-72.274,22.257]],"o":[[0,0],[-19.138,-33.304],[123.75,19.68]],"v":[[131.485,91.18],[70.333,65.557],[140.022,-56.459]],"c":true}]}]},"nm":"Path 1","hd":false},{"ty":"fl","c":{"a":0,"k":[0,0,0,1]},"o":{"a":0,"k":100},"r":1,"bm":0,"nm":"Fill 1","hd":false},{"ty":"tr","p":{"a":0,"k":[0,0]},"a":{"a":0,"k":[0,0]},"s":{"a":0,"k":[100,100]},"r":{"a":0,"k":0},"o":{"a":0,"k":100},"sk":{"a":0,"k":0},"sa":{"a":0,"k":0},"nm":"Transform"}],"nm":"Group 1","bm":0,"hd":false}],"ip":54,"op":720,"st":0,"bm":0},{"ddd":0,"ind":18,"ty":4,"nm":"eyes","parent":13,"sr":1,"ks":{"r":{"a":0,"k":-2.286},"p":{"a":0,"k":[-17.364,0.784,0]},"a":{"a":0,"k":[25.033,1.607,0]},"s":{"a":0,"k":[66,66,100]}},"ao":0,"shapes":[{"ty":"gr","it":[{"ind":0,"ty":"sh","ks":{"a":1,"k":[{"i":{"x":0.667,"y":1},"o":{"x":0.333,"y":0},"t":68,"s":[{"i":[[72.064,0.272],[0,0],[0,0],[-84.128,-1.125],[0,0],[0,0]],"o":[[0,0],[0,0],[-84.128,-1.125],[0,0],[0,0],[72.997,0.338]],"v":[[106.532,66.041],[43.916,65.204],[-74.465,63.62],[-72.774,-62.82],[31.68,-61.423],[108.223,-60.399]],"c":true}]},{"i":{"x":0.667,"y":1},"o":{"x":0.333,"y":0},"t":80,"s":[{"i":[[78.159,0.272],[0,0],[0,0],[-91.244,-1.125],[0,0],[0,0]],"o":[[0,0],[0,0],[-91.244,-1.125],[0,0],[0,0],[79.171,0.338]],"v":[[125.93,66.121],[58.017,65.283],[-70.377,63.699],[-68.543,-62.741],[44.746,-61.344],[127.764,-60.32]],"c":true}]},{"i":{"x":0.667,"y":1},"o":{"x":0.333,"y":0},"t":105,"s":[{"i":[[78.159,0.272],[0,0],[0,0],[-91.244,-1.125],[0,0],[0,0]],"o":[[0,0],[0,0],[-91.244,-1.125],[0,0],[0,0],[79.171,0.338]],"v":[[125.93,66.121],[58.017,65.283],[-70.377,63.699],[-68.543,-62.741],[44.746,-61.344],[127.764,-60.32]],"c":true}]},{"i":{"x":0.667,"y":1},"o":{"x":0.333,"y":0},"t":119,"s":[{"i":[[71.931,-4.388],[0,0],[0,0],[-84.025,4.316],[0,0],[0,0]],"o":[[0,0],[0,0],[-84.025,4.316],[0,0],[0,0],[72.866,-4.383]],"v":[[117.988,60.11],[55.449,63.323],[-62.787,69.396],[-69.274,-56.889],[35.051,-62.248],[111.501,-66.175]],"c":true}]},{"i":{"x":0.667,"y":1},"o":{"x":0.333,"y":0},"t":140,"s":[{"i":[[71.931,-4.388],[0,0],[0,0],[-84.025,4.316],[0,0],[0,0]],"o":[[0,0],[0,0],[-84.025,4.316],[0,0],[0,0],[72.866,-4.383]],"v":[[117.988,60.11],[55.449,63.323],[-62.787,69.396],[-69.274,-56.889],[35.051,-62.248],[111.501,-66.175]],"c":true}]},{"i":{"x":0.667,"y":1},"o":{"x":0.333,"y":0},"t":158,"s":[{"i":[[72.043,3.045],[0,0],[0,0],[-50.939,-2.013],[0,0],[0,0]],"o":[[0,0],[0,0],[-50.939,-2.013],[0,0],[0,0],[72.974,3.147]],"v":[[116.059,67.898],[20.348,62.675],[-45.93,60.32],[-39.042,-65.781],[12.975,-64.33],[122.604,-58.385]],"c":true}]},{"i":{"x":0.667,"y":1},"o":{"x":0.333,"y":0},"t":184,"s":[{"i":[[72.043,3.045],[0,0],[0,0],[-50.939,-2.013],[0,0],[0,0]],"o":[[0,0],[0,0],[-50.939,-2.013],[0,0],[0,0],[72.974,3.147]],"v":[[116.059,67.898],[20.348,62.675],[-45.93,60.32],[-39.042,-65.781],[12.975,-64.33],[122.604,-58.385]],"c":true}]},{"t":200,"s":[{"i":[[72.064,0.272],[0,0],[0,0],[-84.128,-1.125],[0,0],[0,0]],"o":[[0,0],[0,0],[-84.128,-1.125],[0,0],[0,0],[72.997,0.338]],"v":[[106.532,66.041],[43.916,65.204],[-74.465,63.62],[-72.774,-62.82],[31.68,-61.423],[108.223,-60.399]],"c":true}]}]},"nm":"Path 1","hd":false},{"ty":"fl","c":{"a":0,"k":[0,0,0,1]},"o":{"a":0,"k":100},"r":1,"bm":0,"nm":"Fill 1","hd":false},{"ty":"tr","p":{"a":0,"k":[0,0]},"a":{"a":0,"k":[0,0]},"s":{"a":0,"k":[100,100]},"r":{"a":0,"k":0},"o":{"a":0,"k":100},"sk":{"a":0,"k":0},"sa":{"a":0,"k":0},"nm":"Transform"}],"nm":"Group 1","bm":0,"hd":false}],"ip":0,"op":720,"st":0,"bm":0},{"ddd":0,"ind":19,"ty":4,"nm":"head","parent":22,"sr":1,"ks":{"r":{"a":1,"k":[{"i":{"x":[0.667],"y":[1]},"o":{"x":[0.333],"y":[0]},"t":68,"s":[0]},{"i":{"x":[0.667],"y":[1]},"o":{"x":[0.333],"y":[0]},"t":80,"s":[0]},{"i":{"x":[0.667],"y":[1]},"o":{"x":[0.333],"y":[0]},"t":100,"s":[0]},{"i":{"x":[0.667],"y":[1]},"o":{"x":[0.333],"y":[0]},"t":114,"s":[7]},{"i":{"x":[0.667],"y":[1]},"o":{"x":[0.333],"y":[0]},"t":140,"s":[7]},{"i":{"x":[0.667],"y":[1]},"o":{"x":[0.333],"y":[0]},"t":158,"s":[3]},{"i":{"x":[0.667],"y":[1]},"o":{"x":[0.333],"y":[0]},"t":184,"s":[3]},{"t":200,"s":[0]}]},"p":{"a":1,"k":[{"i":{"x":0.667,"y":1},"o":{"x":0.333,"y":0},"t":60,"s":[-51.557,48.045,0],"to":[0,0,0],"ti":[0,0,0]},{"i":{"x":0.667,"y":1},"o":{"x":0.333,"y":0},"t":83,"s":[-51.557,37.281,0],"to":[0,0,0],"ti":[0,0,0]},{"i":{"x":0.667,"y":1},"o":{"x":0.333,"y":0},"t":105,"s":[-51.557,48.045,0],"to":[0,0,0],"ti":[0,0,0]},{"i":{"x":0.667,"y":1},"o":{"x":0.333,"y":0},"t":127.5,"s":[-51.557,37.281,0],"to":[0,0,0],"ti":[0,0,0]},{"i":{"x":0.667,"y":1},"o":{"x":0.333,"y":0},"t":150,"s":[-51.557,48.045,0],"to":[0,0,0],"ti":[0,0,0]},{"i":{"x":0.667,"y":1},"o":{"x":0.333,"y":0},"t":172.5,"s":[-51.557,37.281,0],"to":[0,0,0],"ti":[0,0,0]},{"i":{"x":0.667,"y":1},"o":{"x":0.333,"y":0},"t":195,"s":[-51.557,48.045,0],"to":[0,0,0],"ti":[0,0,0]},{"i":{"x":0.667,"y":1},"o":{"x":0.333,"y":0},"t":217.5,"s":[-51.557,37.281,0],"to":[0,0,0],"ti":[0,0,0]},{"t":240,"s":[-51.557,48.045,0]}]},"a":{"a":0,"k":[-51.557,48.045,0]}},"ao":0,"shapes":[{"ty":"gr","it":[{"ind":0,"ty":"sh","ks":{"a":0,"k":{"i":[[-37.531,42.031],[-0.002,32.584],[77.432,0.005],[0.005,-69.22],[-26.171,-22.358]],"o":[[27.195,-30.456],[0.005,-69.22],[-77.431,-0.005],[-0.002,32.672],[48.328,41.287]],"v":[[54.776,64.759],[97.995,-28.789],[-42.197,-166.159],[-182.407,-28.808],[-147.518,55.05]],"c":true}},"nm":"Path 1","hd":false},{"ty":"st","c":{"a":0,"k":[0.532955035041,0.738938933728,0.870418054917,1]},"o":{"a":0,"k":100},"w":{"a":0,"k":10},"lc":2,"lj":2,"bm":0,"nm":"Stroke 1","hd":false},{"ty":"gf","o":{"a":0,"k":100},"r":1,"bm":0,"g":{"p":3,"k":{"a":0,"k":[0,1,1,1,0.5,0.859,0.967,0.994,1,0.718,0.933,0.987]}},"s":{"a":0,"k":[-62.757,-25.222]},"e":{"a":0,"k":[103.738,54.77]},"t":1,"nm":"faqqwe","hd":false},{"ty":"tr","p":{"a":0,"k":[0,0]},"a":{"a":0,"k":[0,0]},"s":{"a":0,"k":[100,100]},"r":{"a":0,"k":0},"o":{"a":0,"k":100},"sk":{"a":0,"k":0},"sa":{"a":0,"k":0},"nm":"Transform"}],"nm":"Group 1","bm":0,"hd":false}],"ip":0,"op":300,"st":0,"bm":0},{"ddd":0,"ind":20,"ty":4,"nm":"Shape Layer 2","parent":22,"sr":1,"ks":{"o":{"a":0,"k":10},"p":{"a":0,"k":[-44.208,89.41,0]},"a":{"a":0,"k":[113.492,192.016,0]},"s":{"a":0,"k":[76.517,37.044,100]}},"ao":0,"shapes":[{"ty":"gr","it":[{"ind":0,"ty":"sh","ks":{"a":1,"k":[{"i":{"x":0.667,"y":1},"o":{"x":0.333,"y":0},"t":68,"s":[{"i":[[-10.445,-113.42],[56.187,221.315]],"o":[[19.918,216.28],[-21.651,-85.28]],"v":[[144.403,-80.985],[-96.047,-97.181]],"c":true}]},{"i":{"x":0.667,"y":1},"o":{"x":0.333,"y":0},"t":80,"s":[{"i":[[-10.445,-113.42],[56.187,221.315]],"o":[[19.918,216.28],[-21.651,-85.28]],"v":[[144.403,-80.985],[-96.047,-97.181]],"c":true}]},{"i":{"x":0.667,"y":1},"o":{"x":0.333,"y":0},"t":105,"s":[{"i":[[-10.445,-113.42],[56.187,221.315]],"o":[[19.918,216.28],[-21.651,-85.28]],"v":[[144.403,-80.985],[-96.047,-97.181]],"c":true}]},{"i":{"x":0.667,"y":1},"o":{"x":0.333,"y":0},"t":119,"s":[{"i":[[-10.445,-113.42],[56.187,221.315]],"o":[[19.918,216.28],[-21.651,-85.28]],"v":[[144.403,-80.985],[-96.047,-97.181]],"c":true}]},{"i":{"x":0.833,"y":0.833},"o":{"x":0.333,"y":0},"t":140,"s":[{"i":[[-10.445,-113.42],[56.187,221.315]],"o":[[19.918,216.28],[-21.651,-85.28]],"v":[[144.403,-80.985],[-96.047,-97.181]],"c":true}]},{"i":{"x":0.833,"y":0.833},"o":{"x":0.167,"y":0.167},"t":158,"s":[{"i":[[4.506,-113.467],[11.525,206.773]],"o":[[-10.19,234.995],[-4.286,-87.271]],"v":[[129.875,-81.17],[-110.575,-97.367]],"c":true}]},{"i":{"x":0.667,"y":1},"o":{"x":0.167,"y":0.167},"t":184,"s":[{"i":[[4.506,-113.467],[11.525,206.773]],"o":[[-10.19,234.995],[-4.286,-87.271]],"v":[[129.875,-81.17],[-110.575,-97.367]],"c":true}]},{"t":200,"s":[{"i":[[-10.445,-113.42],[56.187,221.315]],"o":[[19.918,216.28],[-21.651,-85.28]],"v":[[144.403,-80.985],[-96.047,-97.181]],"c":true}]}]},"nm":"Path 1","hd":false},{"ty":"fl","c":{"a":0,"k":[0,0.432892952713,0.549034926471,1]},"o":{"a":0,"k":100},"r":1,"bm":0,"nm":"Fill 1","hd":false},{"ty":"tr","p":{"a":0,"k":[113.492,192.016]},"a":{"a":0,"k":[0,0]},"s":{"a":0,"k":[100,100]},"r":{"a":0,"k":0},"o":{"a":0,"k":100},"sk":{"a":0,"k":0},"sa":{"a":0,"k":0},"nm":"Transform"}],"nm":"Ellipse 1","bm":0,"hd":false}],"ip":0,"op":300,"st":0,"bm":0},{"ddd":0,"ind":21,"ty":3,"nm":"NULL CONTROL","sr":1,"ks":{"o":{"a":0,"k":0},"p":{"a":1,"k":[{"i":{"x":0.833,"y":1},"o":{"x":0.333,"y":0},"t":15,"s":[195.725,362.464,0],"to":[20.725,5.464,0],"ti":[-14.166,16.049,0]},{"i":{"x":0.667,"y":1},"o":{"x":0.333,"y":0},"t":75,"s":[259.725,337.464,0],"to":[2.275,12.536,0],"ti":[-5.725,22.536,0]},{"i":{"x":0.667,"y":1},"o":{"x":0.333,"y":0},"t":140,"s":[285.725,342.464,0],"to":[-26.275,30.464,0],"ti":[17.275,6.536,0]},{"i":{"x":0.833,"y":1},"o":{"x":0.333,"y":0},"t":195,"s":[195.725,362.464,0],"to":[20.725,5.464,0],"ti":[-14.166,16.049,0]},{"t":255,"s":[259.725,337.464,0]}]},"a":{"a":0,"k":[60,60,0]}},"ao":0,"ip":0,"op":300,"st":0,"bm":0},{"ddd":0,"ind":22,"ty":4,"nm":"body","parent":21,"sr":1,"ks":{"r":{"a":1,"k":[{"i":{"x":[0.667],"y":[1]},"o":{"x":[0.333],"y":[0]},"t":60,"s":[0]},{"i":{"x":[0.667],"y":[1]},"o":{"x":[0.333],"y":[0]},"t":83,"s":[-5]},{"i":{"x":[0.667],"y":[1]},"o":{"x":[0.333],"y":[0]},"t":97,"s":[0]},{"i":{"x":[0.667],"y":[1]},"o":{"x":[0.333],"y":[0]},"t":124,"s":[-8]},{"i":{"x":[0.667],"y":[1]},"o":{"x":[0.333],"y":[0]},"t":138,"s":[-8]},{"i":{"x":[0.667],"y":[1]},"o":{"x":[0.333],"y":[0]},"t":148,"s":[5]},{"i":{"x":[0.667],"y":[1]},"o":{"x":[0.333],"y":[0]},"t":181,"s":[-2]},{"t":201,"s":[0]}]},"p":{"a":1,"k":[{"i":{"x":0.667,"y":1},"o":{"x":0.333,"y":0},"t":60,"s":[60,60,0],"to":[0,0,0],"ti":[0,0,0]},{"i":{"x":0.667,"y":1},"o":{"x":0.333,"y":0},"t":83,"s":[60,44,0],"to":[0,0,0],"ti":[0,0,0]},{"i":{"x":0.667,"y":1},"o":{"x":0.333,"y":0},"t":105,"s":[60,60,0],"to":[0,0,0],"ti":[0,0,0]},{"i":{"x":0.667,"y":1},"o":{"x":0.333,"y":0},"t":127.5,"s":[60,44,0],"to":[0,0,0],"ti":[0,0,0]},{"i":{"x":0.667,"y":1},"o":{"x":0.333,"y":0},"t":150,"s":[60,60,0],"to":[0,0,0],"ti":[0,0,0]},{"i":{"x":0.667,"y":1},"o":{"x":0.333,"y":0},"t":172.5,"s":[60,44,0],"to":[0,0,0],"ti":[0,0,0]},{"i":{"x":0.667,"y":1},"o":{"x":0.333,"y":0},"t":195,"s":[60,60,0],"to":[0,0,0],"ti":[0,0,0]},{"i":{"x":0.667,"y":1},"o":{"x":0.333,"y":0},"t":217.5,"s":[60,44,0],"to":[0,0,0],"ti":[0,0,0]},{"t":240,"s":[60,60,0]}]},"a":{"a":0,"k":[-45.275,126.464,0]},"s":{"a":1,"k":[{"i":{"x":[0.595,0.595,0.595],"y":[1,1,1]},"o":{"x":[0.254,0.254,0.254],"y":[0,0,0]},"t":68,"s":[100,100,100]},{"i":{"x":[0.661,0.661,0.661],"y":[0.954,0.942,1]},"o":{"x":[0.29,0.29,0.29],"y":[0,0,0]},"t":76,"s":[102,95.355,100]},{"i":{"x":[0.833,0.833,0.833],"y":[1,1,1]},"o":{"x":[0.329,0.329,0.329],"y":[-0.09,0.26,0]},"t":88,"s":[100,100,100]},{"i":{"x":[0.595,0.595,0.595],"y":[1,1,1]},"o":{"x":[0.254,0.254,0.254],"y":[0,0,0]},"t":100,"s":[100,100,100]},{"i":{"x":[0.661,0.661,0.661],"y":[0.954,0.942,1]},"o":{"x":[0.29,0.29,0.29],"y":[0,0,0]},"t":108,"s":[102,95.355,100]},{"i":{"x":[0.833,0.833,0.833],"y":[1,1,1]},"o":{"x":[0.338,0.338,0.338],"y":[-0.154,0.445,0]},"t":120,"s":[100,100,100]},{"i":{"x":[0.595,0.595,0.595],"y":[1,1,1]},"o":{"x":[0.254,0.254,0.254],"y":[0,0,0]},"t":140,"s":[100,100,100]},{"i":{"x":[0.661,0.661,0.661],"y":[0.954,0.942,1]},"o":{"x":[0.29,0.29,0.29],"y":[0,0,0]},"t":148,"s":[102,95.355,100]},{"i":{"x":[0.833,0.833,0.833],"y":[1,1,1]},"o":{"x":[0.329,0.329,0.329],"y":[0,0,0]},"t":160,"s":[100,100,100]},{"i":{"x":[0.595,0.595,0.595],"y":[1,1,1]},"o":{"x":[0.254,0.254,0.254],"y":[0,0,0]},"t":184,"s":[100,100,100]},{"i":{"x":[0.661,0.661,0.661],"y":[0.954,0.942,1]},"o":{"x":[0.29,0.29,0.29],"y":[0,0,0]},"t":192,"s":[102,95.355,100]},{"t":204,"s":[100,100,100]}]}},"ao":0,"shapes":[{"ty":"gr","it":[{"ind":0,"ty":"sh","ks":{"a":0,"k":{"i":[[0,-48.995],[-58.662,0.554],[0,67.61],[65.247,0.252]],"o":[[0,74.213],[58.085,-0.549],[0,-45.694],[-62.783,-0.242]],"v":[[-163.843,86.693],[-45.295,242.297],[73.292,86.211],[-48.973,15.321]],"c":true}},"nm":"Path 1","hd":false},{"ty":"st","c":{"a":0,"k":[0.532955035041,0.738938933728,0.870418054917,1]},"o":{"a":0,"k":100},"w":{"a":0,"k":10},"lc":2,"lj":2,"bm":0,"nm":"Stroke 1","hd":false},{"ty":"gf","o":{"a":0,"k":100},"r":1,"bm":0,"g":{"p":3,"k":{"a":0,"k":[0,1,1,1,0.5,0.859,0.967,0.994,1,0.718,0.933,0.987]}},"s":{"a":0,"k":[-106.86,69.529]},"e":{"a":0,"k":[100.511,98.975]},"t":1,"nm":"faqqwe","hd":false},{"ty":"tr","p":{"a":0,"k":[0,0]},"a":{"a":0,"k":[0,0]},"s":{"a":0,"k":[100,100]},"r":{"a":0,"k":0},"o":{"a":0,"k":100},"sk":{"a":0,"k":0},"sa":{"a":0,"k":0},"nm":"Transform"}],"nm":"Group 1","bm":0,"hd":false}],"ip":0,"op":300,"st":0,"bm":0},{"ddd":0,"ind":23,"ty":4,"nm":"wing 2","parent":22,"sr":1,"ks":{"p":{"a":0,"k":[71,76,0]},"a":{"a":0,"k":[-109,126,0]}},"ao":0,"shapes":[{"ty":"gr","it":[{"ind":0,"ty":"sh","ks":{"a":1,"k":[{"i":{"x":0.667,"y":1},"o":{"x":0.333,"y":0},"t":68,"s":[{"i":[[0,0],[-8.57,-6.834],[31.779,2.611]],"o":[[30.987,-12.116],[23.514,18.753],[0,0]],"v":[[-116.987,130.116],[-59.014,119.247],[-115.779,169.389]],"c":false}]},{"i":{"x":0.667,"y":1},"o":{"x":0.333,"y":0},"t":86,"s":[{"i":[[0,0],[-8.57,-6.834],[34.687,10.569]],"o":[[38.36,8.962],[23.514,18.753],[0,0]],"v":[[-116.987,130.116],[-29.442,133.219],[-113.807,178.704]],"c":false}]},{"i":{"x":0.667,"y":1},"o":{"x":0.333,"y":0},"t":105,"s":[{"i":[[0,0],[-8.57,-6.834],[34.687,10.569]],"o":[[38.36,8.962],[23.514,18.753],[0,0]],"v":[[-116.987,130.116],[-29.442,133.219],[-113.807,178.704]],"c":false}]},{"i":{"x":0.667,"y":1},"o":{"x":0.333,"y":0},"t":119,"s":[{"i":[[0,0],[-8.57,-6.834],[61.566,0.107]],"o":[[44.484,25.593],[23.514,18.753],[0,0]],"v":[[-126.76,111.854],[-34.693,101.169],[-126.001,184.223]],"c":false}]},{"i":{"x":0.667,"y":1},"o":{"x":0.333,"y":0},"t":140,"s":[{"i":[[0,0],[-8.57,-6.834],[61.566,0.107]],"o":[[44.484,25.593],[23.514,18.753],[0,0]],"v":[[-126.76,111.854],[-34.693,101.169],[-126.001,184.223]],"c":false}]},{"i":{"x":0.667,"y":1},"o":{"x":0.333,"y":0},"t":158,"s":[{"i":[[0,0],[-0.071,-10.961],[20.091,-9.571]],"o":[[28.03,-2.145],[0.127,19.565],[0,0]],"v":[[-130.601,117.902],[-95.999,141.056],[-121.975,186.654]],"c":false}]},{"i":{"x":0.667,"y":1},"o":{"x":0.333,"y":0},"t":184,"s":[{"i":[[0,0],[-0.071,-10.961],[20.091,-9.571]],"o":[[28.03,-2.145],[0.127,19.565],[0,0]],"v":[[-130.601,117.902],[-95.999,141.056],[-121.975,186.654]],"c":false}]},{"t":199,"s":[{"i":[[0,0],[-8.57,-6.834],[31.779,2.611]],"o":[[30.987,-12.116],[23.514,18.753],[0,0]],"v":[[-116.987,130.116],[-59.014,119.247],[-115.779,169.389]],"c":false}]}]},"nm":"Path 1","hd":false},{"ty":"st","c":{"a":0,"k":[0.533333333333,0.737254901961,0.870588235294,1]},"o":{"a":0,"k":100},"w":{"a":0,"k":10},"lc":2,"lj":2,"bm":0,"nm":"Stroke 1","hd":false},{"ty":"fl","c":{"a":0,"k":[0.788235353956,0.949019667682,0.992156922583,1]},"o":{"a":0,"k":100},"r":1,"bm":0,"nm":"Fill 1","hd":false},{"ty":"tr","p":{"a":0,"k":[0,0]},"a":{"a":0,"k":[0,0]},"s":{"a":0,"k":[100,100]},"r":{"a":0,"k":0},"o":{"a":0,"k":100},"sk":{"a":0,"k":0},"sa":{"a":0,"k":0},"nm":"Transform"}],"nm":"Group 2","bm":0,"hd":false}],"ip":0,"op":300,"st":0,"bm":0}]}